{
  "sample": "spmv_kernel",
  "device": "Tesla V100-SXM2-32GB",
  "platform_version": "CUDA driver 10020",
  "device_vendor": "NVIDIA Corporation",
  "device_type": "GPU",
  "device_core_clock": "1530",
  "device_compute_units": "80",
  "device_extra_info": "SM 7.0",
  "results": [
    {
      "kernel": "spmv_kernel",
      "time": 0.257,
      "parameters": {"BLOCK_SIZE": 807,"PRECISION": 64,"FORMAT": 1,"UNROLL_LOOP_1": 1,"UNROLL_LOOP_2": 0,"THREADS_PER_ROW": 1,"TEXTURE_MEMORY": 0}
    },
    {
      "kernel": "spmv_kernel",
      "time": 0.207,
      "parameters": {"BLOCK_SIZE": 254,"PRECISION": 64,"FORMAT": 0,"UNROLL_LOOP_1": 0,"UNROLL_LOOP_2": 0,"THREADS_PER_ROW": 1,"TEXTURE_MEMORY": 0}
    },
    {
      "kernel": "spmv_kernel",
      "time": 0.342,
      "parameters": {"BLOCK_SIZE": 960,"PRECISION": 64,"FORMAT": 1,"UNROLL_LOOP_1": 0,"UNROLL_LOOP_2": 0,"THREADS_PER_ROW": 1,"TEXTURE_MEMORY": 0}
    },
    {
      "kernel": "spmv_kernel",
      "time": 0.112,
      "parameters": {"BLOCK_SIZE": 650,"PRECISION": 64,"FORMAT": 0,"UNROLL_LOOP_1": 1,"UNROLL_LOOP_2": 0,"THREADS_PER_ROW": 1,"TEXTURE_MEMORY": 0}
    },
    {
      "kernel": "spmv_kernel",
      "time": 0.228,
      "parameters": {"BLOCK_SIZE": 986,"PRECISION": 64,"FORMAT": 0,"UNROLL_LOOP_1": 0,"UNROLL_LOOP_2": 0,"THREADS_PER_ROW": 1,"TEXTURE_MEMORY": 0}
    },
    {
      "kernel": "spmv_kernel",
      "time": 0.292,
      "parameters": {"BLOCK_SIZE": 807,"PRECISION": 64,"FORMAT": 1,"UNROLL_LOOP_1": 0,"UNROLL_LOOP_2": 0,"THREADS_PER_ROW": 1,"TEXTURE_MEMORY": 0}
    },
    {
      "kernel": "spmv_kernel",
      "time": 0.206,
      "parameters": {"BLOCK_SIZE": 254,"PRECISION": 64,"FORMAT": 0,"UNROLL_LOOP_1": 0,"UNROLL_LOOP_2": 0,"THREADS_PER_ROW": 1,"TEXTURE_MEMORY": 0}
    },
    {
      "kernel": "spmv_kernel",
      "time": 0.338,
      "parameters": {"BLOCK_SIZE": 960,"PRECISION": 64,"FORMAT": 1,"UNROLL_LOOP_1": 0,"UNROLL_LOOP_2": 0,"THREADS_PER_ROW": 1,"TEXTURE_MEMORY": 0}
    },
    {
      "kernel": "spmv_kernel",
      "time": 0.112,
      "parameters": {"BLOCK_SIZE": 650,"PRECISION": 64,"FORMAT": 0,"UNROLL_LOOP_1": 1,"UNROLL_LOOP_2": 0,"THREADS_PER_ROW": 1,"TEXTURE_MEMORY": 0}
    },
    {
      "kernel": "spmv_kernel",
      "time": 0.129,
      "parameters": {"BLOCK_SIZE": 986,"PRECISION": 64,"FORMAT": 0,"UNROLL_LOOP_1": 1,"UNROLL_LOOP_2": 0,"THREADS_PER_ROW": 1,"TEXTURE_MEMORY": 0}
    },
    {
      "kernel": "spmv_kernel",
      "time": 0.199,
      "parameters": {"BLOCK_SIZE": 650,"PRECISION": 64,"FORMAT": 1,"UNROLL_LOOP_1": 1,"UNROLL_LOOP_2": 0,"THREADS_PER_ROW": 1,"TEXTURE_MEMORY": 0}
    },
    {
      "kernel": "spmv_kernel",
      "time": 0.215,
      "parameters": {"BLOCK_SIZE": 850,"PRECISION": 64,"FORMAT": 0,"UNROLL_LOOP_1": 0,"UNROLL_LOOP_2": 0,"THREADS_PER_ROW": 1,"TEXTURE_MEMORY": 0}
    },
    {
      "kernel": "spmv_kernel",
      "time": 0.215,
      "parameters": {"BLOCK_SIZE": 680,"PRECISION": 64,"FORMAT": 0,"UNROLL_LOOP_1": 0,"UNROLL_LOOP_2": 0,"THREADS_PER_ROW": 1,"TEXTURE_MEMORY": 0}
    },
    {
      "kernel": "spmv_kernel",
      "time": 0.110,
      "parameters": {"BLOCK_SIZE": 650,"PRECISION": 64,"FORMAT": 0,"UNROLL_LOOP_1": 1,"UNROLL_LOOP_2": 0,"THREADS_PER_ROW": 1,"TEXTURE_MEMORY": 0}
    },
    {
      "kernel": "spmv_kernel",
      "time": 0.111,
      "parameters": {"BLOCK_SIZE": 650,"PRECISION": 64,"FORMAT": 0,"UNROLL_LOOP_1": 1,"UNROLL_LOOP_2": 0,"THREADS_PER_ROW": 1,"TEXTURE_MEMORY": 0}
    },
    {
      "kernel": "spmv_kernel",
      "time": 0.111,
      "parameters": {"BLOCK_SIZE": 650,"PRECISION": 64,"FORMAT": 0,"UNROLL_LOOP_1": 1,"UNROLL_LOOP_2": 0,"THREADS_PER_ROW": 1,"TEXTURE_MEMORY": 0}
    },
    {
      "kernel": "spmv_kernel",
      "time": 0.215,
      "parameters": {"BLOCK_SIZE": 850,"PRECISION": 64,"FORMAT": 0,"UNROLL_LOOP_1": 0,"UNROLL_LOOP_2": 0,"THREADS_PER_ROW": 1,"TEXTURE_MEMORY": 0}
    },
    {
      "kernel": "spmv_kernel",
      "time": 0.252,
      "parameters": {"BLOCK_SIZE": 676,"PRECISION": 64,"FORMAT": 2,"UNROLL_LOOP_1": 1,"UNROLL_LOOP_2": 0,"THREADS_PER_ROW": 1,"TEXTURE_MEMORY": 0}
    },
    {
      "kernel": "spmv_kernel",
      "time": 0.112,
      "parameters": {"BLOCK_SIZE": 650,"PRECISION": 64,"FORMAT": 0,"UNROLL_LOOP_1": 1,"UNROLL_LOOP_2": 0,"THREADS_PER_ROW": 1,"TEXTURE_MEMORY": 0}
    },
    {
      "kernel": "spmv_kernel",
      "time": 0.112,
      "parameters": {"BLOCK_SIZE": 650,"PRECISION": 64,"FORMAT": 0,"UNROLL_LOOP_1": 1,"UNROLL_LOOP_2": 0,"THREADS_PER_ROW": 1,"TEXTURE_MEMORY": 0}
    },
    {
      "kernel": "spmv_kernel",
      "time": 0.110,
      "parameters": {"BLOCK_SIZE": 650,"PRECISION": 64,"FORMAT": 0,"UNROLL_LOOP_1": 1,"UNROLL_LOOP_2": 0,"THREADS_PER_ROW": 1,"TEXTURE_MEMORY": 0}
    },
    {
      "kernel": "spmv_kernel",
      "time": 0.125,
      "parameters": {"BLOCK_SIZE": 954,"PRECISION": 64,"FORMAT": 0,"UNROLL_LOOP_1": 1,"UNROLL_LOOP_2": 0,"THREADS_PER_ROW": 1,"TEXTURE_MEMORY": 0}
    },
    {
      "kernel": "spmv_kernel",
      "time": 0.114,
      "parameters": {"BLOCK_SIZE": 676,"PRECISION": 64,"FORMAT": 0,"UNROLL_LOOP_1": 1,"UNROLL_LOOP_2": 0,"THREADS_PER_ROW": 1,"TEXTURE_MEMORY": 0}
    },
    {
      "kernel": "spmv_kernel",
      "time": 0.110,
      "parameters": {"BLOCK_SIZE": 650,"PRECISION": 64,"FORMAT": 0,"UNROLL_LOOP_1": 1,"UNROLL_LOOP_2": 0,"THREADS_PER_ROW": 1,"TEXTURE_MEMORY": 0}
    },
    {
      "kernel": "spmv_kernel",
      "time": 0.111,
      "parameters": {"BLOCK_SIZE": 650,"PRECISION": 64,"FORMAT": 0,"UNROLL_LOOP_1": 1,"UNROLL_LOOP_2": 0,"THREADS_PER_ROW": 1,"TEXTURE_MEMORY": 0}
    },
    {
      "kernel": "spmv_kernel",
      "time": 0.112,
      "parameters": {"BLOCK_SIZE": 650,"PRECISION": 64,"FORMAT": 0,"UNROLL_LOOP_1": 1,"UNROLL_LOOP_2": 0,"THREADS_PER_ROW": 1,"TEXTURE_MEMORY": 0}
    },
    {
      "kernel": "spmv_kernel",
      "time": 0.112,
      "parameters": {"BLOCK_SIZE": 954,"PRECISION": 32,"FORMAT": 0,"UNROLL_LOOP_1": 1,"UNROLL_LOOP_2": 0,"THREADS_PER_ROW": 1,"TEXTURE_MEMORY": 0}
    },
    {
      "kernel": "spmv_kernel",
      "time": 0.114,
      "parameters": {"BLOCK_SIZE": 676,"PRECISION": 64,"FORMAT": 0,"UNROLL_LOOP_1": 1,"UNROLL_LOOP_2": 0,"THREADS_PER_ROW": 1,"TEXTURE_MEMORY": 0}
    },
    {
      "kernel": "spmv_kernel",
      "time": 0.132,
      "parameters": {"BLOCK_SIZE": 875,"PRECISION": 64,"FORMAT": 0,"UNROLL_LOOP_1": 1,"UNROLL_LOOP_2": 0,"THREADS_PER_ROW": 1,"TEXTURE_MEMORY": 0}
    },
    {
      "kernel": "spmv_kernel",
      "time": 0.114,
      "parameters": {"BLOCK_SIZE": 650,"PRECISION": 64,"FORMAT": 0,"UNROLL_LOOP_1": 1,"UNROLL_LOOP_2": 0,"THREADS_PER_ROW": 1,"TEXTURE_MEMORY": 0}
    },
    {
      "kernel": "spmv_kernel",
      "time": 0.110,
      "parameters": {"BLOCK_SIZE": 650,"PRECISION": 64,"FORMAT": 0,"UNROLL_LOOP_1": 1,"UNROLL_LOOP_2": 0,"THREADS_PER_ROW": 1,"TEXTURE_MEMORY": 0}
    },
    {
      "kernel": "spmv_kernel",
      "time": 0.126,
      "parameters": {"BLOCK_SIZE": 954,"PRECISION": 64,"FORMAT": 0,"UNROLL_LOOP_1": 1,"UNROLL_LOOP_2": 0,"THREADS_PER_ROW": 1,"TEXTURE_MEMORY": 0}
    },
    {
      "kernel": "spmv_kernel",
      "time": 0.253,
      "parameters": {"BLOCK_SIZE": 676,"PRECISION": 64,"FORMAT": 2,"UNROLL_LOOP_1": 1,"UNROLL_LOOP_2": 0,"THREADS_PER_ROW": 1,"TEXTURE_MEMORY": 0}
    },
    {
      "kernel": "spmv_kernel",
      "time": 0.098,
      "parameters": {"BLOCK_SIZE": 737,"PRECISION": 32,"FORMAT": 0,"UNROLL_LOOP_1": 1,"UNROLL_LOOP_2": 0,"THREADS_PER_ROW": 1,"TEXTURE_MEMORY": 0}
    },
    {
      "kernel": "spmv_kernel",
      "time": 0.123,
      "parameters": {"BLOCK_SIZE": 662,"PRECISION": 64,"FORMAT": 0,"UNROLL_LOOP_1": 1,"UNROLL_LOOP_2": 0,"THREADS_PER_ROW": 1,"TEXTURE_MEMORY": 0}
    },
    {
      "kernel": "spmv_kernel",
      "time": 0.133,
      "parameters": {"BLOCK_SIZE": 305,"PRECISION": 64,"FORMAT": 2,"UNROLL_LOOP_1": 1,"UNROLL_LOOP_2": 0,"THREADS_PER_ROW": 1,"TEXTURE_MEMORY": 0}
    },
    {
      "kernel": "spmv_kernel",
      "time": 0.126,
      "parameters": {"BLOCK_SIZE": 963,"PRECISION": 64,"FORMAT": 0,"UNROLL_LOOP_1": 1,"UNROLL_LOOP_2": 0,"THREADS_PER_ROW": 1,"TEXTURE_MEMORY": 0}
    },
    {
      "kernel": "spmv_kernel",
      "time": 0.122,
      "parameters": {"BLOCK_SIZE": 888,"PRECISION": 64,"FORMAT": 0,"UNROLL_LOOP_1": 1,"UNROLL_LOOP_2": 0,"THREADS_PER_ROW": 1,"TEXTURE_MEMORY": 0}
    },
    {
      "kernel": "spmv_kernel",
      "time": 0.227,
      "parameters": {"BLOCK_SIZE": 737,"PRECISION": 32,"FORMAT": 2,"UNROLL_LOOP_1": 1,"UNROLL_LOOP_2": 0,"THREADS_PER_ROW": 1,"TEXTURE_MEMORY": 0}
    },
    {
      "kernel": "spmv_kernel",
      "time": 0.123,
      "parameters": {"BLOCK_SIZE": 662,"PRECISION": 64,"FORMAT": 0,"UNROLL_LOOP_1": 1,"UNROLL_LOOP_2": 0,"THREADS_PER_ROW": 1,"TEXTURE_MEMORY": 0}
    },
    {
      "kernel": "spmv_kernel",
      "time": 0.098,
      "parameters": {"BLOCK_SIZE": 737,"PRECISION": 32,"FORMAT": 0,"UNROLL_LOOP_1": 1,"UNROLL_LOOP_2": 0,"THREADS_PER_ROW": 1,"TEXTURE_MEMORY": 0}
    },
    {
      "kernel": "spmv_kernel",
      "time": 0.098,
      "parameters": {"BLOCK_SIZE": 737,"PRECISION": 32,"FORMAT": 0,"UNROLL_LOOP_1": 1,"UNROLL_LOOP_2": 0,"THREADS_PER_ROW": 1,"TEXTURE_MEMORY": 0}
    },
    {
      "kernel": "spmv_kernel",
      "time": 0.102,
      "parameters": {"BLOCK_SIZE": 796,"PRECISION": 32,"FORMAT": 0,"UNROLL_LOOP_1": 1,"UNROLL_LOOP_2": 0,"THREADS_PER_ROW": 1,"TEXTURE_MEMORY": 0}
    },
    {
      "kernel": "spmv_kernel",
      "time": 0.098,
      "parameters": {"BLOCK_SIZE": 737,"PRECISION": 32,"FORMAT": 0,"UNROLL_LOOP_1": 1,"UNROLL_LOOP_2": 0,"THREADS_PER_ROW": 1,"TEXTURE_MEMORY": 0}
    },
    {
      "kernel": "spmv_kernel",
      "time": 0.097,
      "parameters": {"BLOCK_SIZE": 662,"PRECISION": 32,"FORMAT": 0,"UNROLL_LOOP_1": 1,"UNROLL_LOOP_2": 0,"THREADS_PER_ROW": 1,"TEXTURE_MEMORY": 0}
    },
    {
      "kernel": "spmv_kernel",
      "time": 0.098,
      "parameters": {"BLOCK_SIZE": 737,"PRECISION": 32,"FORMAT": 0,"UNROLL_LOOP_1": 1,"UNROLL_LOOP_2": 0,"THREADS_PER_ROW": 1,"TEXTURE_MEMORY": 0}
    },
    {
      "kernel": "spmv_kernel",
      "time": 0.207,
      "parameters": {"BLOCK_SIZE": 928,"PRECISION": 32,"FORMAT": 0,"UNROLL_LOOP_1": 0,"UNROLL_LOOP_2": 0,"THREADS_PER_ROW": 1,"TEXTURE_MEMORY": 0}
    },
    {
      "kernel": "spmv_kernel",
      "time": 0.099,
      "parameters": {"BLOCK_SIZE": 737,"PRECISION": 32,"FORMAT": 0,"UNROLL_LOOP_1": 1,"UNROLL_LOOP_2": 0,"THREADS_PER_ROW": 1,"TEXTURE_MEMORY": 0}
    },
    {
      "kernel": "spmv_kernel",
      "time": 0.100,
      "parameters": {"BLOCK_SIZE": 737,"PRECISION": 32,"FORMAT": 0,"UNROLL_LOOP_1": 1,"UNROLL_LOOP_2": 0,"THREADS_PER_ROW": 1,"TEXTURE_MEMORY": 0}
    },
    {
      "kernel": "spmv_kernel",
      "time": 0.098,
      "parameters": {"BLOCK_SIZE": 662,"PRECISION": 32,"FORMAT": 0,"UNROLL_LOOP_1": 1,"UNROLL_LOOP_2": 0,"THREADS_PER_ROW": 1,"TEXTURE_MEMORY": 0}
    },
    {
      "kernel": "spmv_kernel",
      "time": 0.098,
      "parameters": {"BLOCK_SIZE": 662,"PRECISION": 32,"FORMAT": 0,"UNROLL_LOOP_1": 1,"UNROLL_LOOP_2": 0,"THREADS_PER_ROW": 1,"TEXTURE_MEMORY": 0}
    },
    {
      "kernel": "spmv_kernel",
      "time": 0.098,
      "parameters": {"BLOCK_SIZE": 662,"PRECISION": 32,"FORMAT": 0,"UNROLL_LOOP_1": 1,"UNROLL_LOOP_2": 0,"THREADS_PER_ROW": 1,"TEXTURE_MEMORY": 0}
    },
    {
      "kernel": "spmv_kernel",
      "time": 0.098,
      "parameters": {"BLOCK_SIZE": 662,"PRECISION": 32,"FORMAT": 0,"UNROLL_LOOP_1": 1,"UNROLL_LOOP_2": 0,"THREADS_PER_ROW": 1,"TEXTURE_MEMORY": 0}
    },
    {
      "kernel": "spmv_kernel",
      "time": 0.088,
      "parameters": {"BLOCK_SIZE": 494,"PRECISION": 32,"FORMAT": 0,"UNROLL_LOOP_1": 1,"UNROLL_LOOP_2": 0,"THREADS_PER_ROW": 1,"TEXTURE_MEMORY": 0}
    },
    {
      "kernel": "spmv_kernel",
      "time": 0.110,
      "parameters": {"BLOCK_SIZE": 894,"PRECISION": 32,"FORMAT": 0,"UNROLL_LOOP_1": 1,"UNROLL_LOOP_2": 0,"THREADS_PER_ROW": 1,"TEXTURE_MEMORY": 0}
    },
    {
      "kernel": "spmv_kernel",
      "time": 0.097,
      "parameters": {"BLOCK_SIZE": 662,"PRECISION": 32,"FORMAT": 0,"UNROLL_LOOP_1": 1,"UNROLL_LOOP_2": 0,"THREADS_PER_ROW": 1,"TEXTURE_MEMORY": 0}
    },
    {
      "kernel": "spmv_kernel",
      "time": 0.142,
      "parameters": {"BLOCK_SIZE": 820,"PRECISION": 64,"FORMAT": 0,"UNROLL_LOOP_1": 1,"UNROLL_LOOP_2": 0,"THREADS_PER_ROW": 1,"TEXTURE_MEMORY": 0}
    },
    {
      "kernel": "spmv_kernel",
      "time": 0.098,
      "parameters": {"BLOCK_SIZE": 662,"PRECISION": 32,"FORMAT": 0,"UNROLL_LOOP_1": 1,"UNROLL_LOOP_2": 0,"THREADS_PER_ROW": 1,"TEXTURE_MEMORY": 0}
    },
    {
      "kernel": "spmv_kernel",
      "time": 0.089,
      "parameters": {"BLOCK_SIZE": 494,"PRECISION": 32,"FORMAT": 0,"UNROLL_LOOP_1": 1,"UNROLL_LOOP_2": 0,"THREADS_PER_ROW": 1,"TEXTURE_MEMORY": 0}
    },
    {
      "kernel": "spmv_kernel",
      "time": 0.090,
      "parameters": {"BLOCK_SIZE": 494,"PRECISION": 32,"FORMAT": 0,"UNROLL_LOOP_1": 1,"UNROLL_LOOP_2": 0,"THREADS_PER_ROW": 1,"TEXTURE_MEMORY": 0}
    },
    {
      "kernel": "spmv_kernel",
      "time": 0.099,
      "parameters": {"BLOCK_SIZE": 662,"PRECISION": 32,"FORMAT": 0,"UNROLL_LOOP_1": 1,"UNROLL_LOOP_2": 0,"THREADS_PER_ROW": 1,"TEXTURE_MEMORY": 0}
    },
    {
      "kernel": "spmv_kernel",
      "time": 0.144,
      "parameters": {"BLOCK_SIZE": 820,"PRECISION": 64,"FORMAT": 0,"UNROLL_LOOP_1": 1,"UNROLL_LOOP_2": 0,"THREADS_PER_ROW": 1,"TEXTURE_MEMORY": 0}
    },
    {
      "kernel": "spmv_kernel",
      "time": 0.102,
      "parameters": {"BLOCK_SIZE": 608,"PRECISION": 32,"FORMAT": 0,"UNROLL_LOOP_1": 1,"UNROLL_LOOP_2": 0,"THREADS_PER_ROW": 1,"TEXTURE_MEMORY": 0}
    }
  ]
}
