{
  "sample": "spmv_kernel",
  "device": "GeForce GTX 980",
  "platform_version": "CUDA driver 11000",
  "device_vendor": "NVIDIA Corporation",
  "device_type": "GPU",
  "device_core_clock": "1215",
  "device_compute_units": "16",
  "device_extra_info": "SM 5.2",
  "results": [
    {
      "kernel": "spmv_kernel",
      "time": 0.377,
      "parameters": {"BLOCK_SIZE": 247,"PRECISION": 32,"FORMAT": 0,"UNROLL_LOOP_1": 1,"UNROLL_LOOP_2": 0,"THREADS_PER_ROW": 1,"TEXTURE_MEMORY": 0}
    },
    {
      "kernel": "spmv_kernel",
      "time": 0.687,
      "parameters": {"BLOCK_SIZE": 225,"PRECISION": 32,"FORMAT": 2,"UNROLL_LOOP_1": 1,"UNROLL_LOOP_2": 0,"THREADS_PER_ROW": 1,"TEXTURE_MEMORY": 0}
    },
    {
      "kernel": "spmv_kernel",
      "time": 0.672,
      "parameters": {"BLOCK_SIZE": 206,"PRECISION": 32,"FORMAT": 2,"UNROLL_LOOP_1": 1,"UNROLL_LOOP_2": 0,"THREADS_PER_ROW": 1,"TEXTURE_MEMORY": 0}
    },
    {
      "kernel": "spmv_kernel",
      "time": 0.789,
      "parameters": {"BLOCK_SIZE": 721,"PRECISION": 64,"FORMAT": 2,"UNROLL_LOOP_1": 1,"UNROLL_LOOP_2": 0,"THREADS_PER_ROW": 1,"TEXTURE_MEMORY": 0}
    },
    {
      "kernel": "spmv_kernel",
      "time": 1.122,
      "parameters": {"BLOCK_SIZE": 800,"PRECISION": 64,"FORMAT": 1,"UNROLL_LOOP_1": 1,"UNROLL_LOOP_2": 0,"THREADS_PER_ROW": 1,"TEXTURE_MEMORY": 0}
    },
    {
      "kernel": "spmv_kernel",
      "time": 1.109,
      "parameters": {"BLOCK_SIZE": 490,"PRECISION": 64,"FORMAT": 1,"UNROLL_LOOP_1": 1,"UNROLL_LOOP_2": 0,"THREADS_PER_ROW": 1,"TEXTURE_MEMORY": 0}
    },
    {
      "kernel": "spmv_kernel",
      "time": 1.035,
      "parameters": {"BLOCK_SIZE": 329,"PRECISION": 64,"FORMAT": 1,"UNROLL_LOOP_1": 1,"UNROLL_LOOP_2": 0,"THREADS_PER_ROW": 1,"TEXTURE_MEMORY": 0}
    },
    {
      "kernel": "spmv_kernel",
      "time": 0.425,
      "parameters": {"BLOCK_SIZE": 6,"PRECISION": 64,"FORMAT": 0,"UNROLL_LOOP_1": 1,"UNROLL_LOOP_2": 0,"THREADS_PER_ROW": 1,"TEXTURE_MEMORY": 0}
    },
    {
      "kernel": "spmv_kernel",
      "time": 0.376,
      "parameters": {"BLOCK_SIZE": 163,"PRECISION": 32,"FORMAT": 0,"UNROLL_LOOP_1": 1,"UNROLL_LOOP_2": 0,"THREADS_PER_ROW": 1,"TEXTURE_MEMORY": 0}
    },
    {
      "kernel": "spmv_kernel",
      "time": 1.894,
      "parameters": {"BLOCK_SIZE": 64,"PRECISION": 32,"FORMAT": 2,"UNROLL_LOOP_1": 0,"UNROLL_LOOP_2": 0,"THREADS_PER_ROW": 1,"TEXTURE_MEMORY": 0}
    },
    {
      "kernel": "spmv_kernel",
      "time": 0.453,
      "parameters": {"BLOCK_SIZE": 457,"PRECISION": 32,"FORMAT": 0,"UNROLL_LOOP_1": 0,"UNROLL_LOOP_2": 0,"THREADS_PER_ROW": 1,"TEXTURE_MEMORY": 0}
    },
    {
      "kernel": "spmv_kernel",
      "time": 0.400,
      "parameters": {"BLOCK_SIZE": 253,"PRECISION": 32,"FORMAT": 0,"UNROLL_LOOP_1": 1,"UNROLL_LOOP_2": 0,"THREADS_PER_ROW": 1,"TEXTURE_MEMORY": 0}
    },
    {
      "kernel": "spmv_kernel",
      "time": 0.708,
      "parameters": {"BLOCK_SIZE": 306,"PRECISION": 64,"FORMAT": 2,"UNROLL_LOOP_1": 1,"UNROLL_LOOP_2": 0,"THREADS_PER_ROW": 1,"TEXTURE_MEMORY": 0}
    },
    {
      "kernel": "spmv_kernel",
      "time": 0.934,
      "parameters": {"BLOCK_SIZE": 818,"PRECISION": 32,"FORMAT": 1,"UNROLL_LOOP_1": 1,"UNROLL_LOOP_2": 0,"THREADS_PER_ROW": 1,"TEXTURE_MEMORY": 0}
    },
    {
      "kernel": "spmv_kernel",
      "time": 0.965,
      "parameters": {"BLOCK_SIZE": 90,"PRECISION": 64,"FORMAT": 1,"UNROLL_LOOP_1": 1,"UNROLL_LOOP_2": 0,"THREADS_PER_ROW": 1,"TEXTURE_MEMORY": 0}
    },
    {
      "kernel": "spmv_kernel",
      "time": 1.739,
      "parameters": {"BLOCK_SIZE": 195,"PRECISION": 32,"FORMAT": 1,"UNROLL_LOOP_1": 0,"UNROLL_LOOP_2": 0,"THREADS_PER_ROW": 1,"TEXTURE_MEMORY": 0}
    },
    {
      "kernel": "spmv_kernel",
      "time": 2.082,
      "parameters": {"BLOCK_SIZE": 223,"PRECISION": 64,"FORMAT": 2,"UNROLL_LOOP_1": 0,"UNROLL_LOOP_2": 0,"THREADS_PER_ROW": 1,"TEXTURE_MEMORY": 0}
    },
    {
      "kernel": "spmv_kernel",
      "time": 1.018,
      "parameters": {"BLOCK_SIZE": 969,"PRECISION": 64,"FORMAT": 2,"UNROLL_LOOP_1": 1,"UNROLL_LOOP_2": 0,"THREADS_PER_ROW": 1,"TEXTURE_MEMORY": 0}
    },
    {
      "kernel": "spmv_kernel",
      "time": 0.389,
      "parameters": {"BLOCK_SIZE": 87,"PRECISION": 32,"FORMAT": 0,"UNROLL_LOOP_1": 1,"UNROLL_LOOP_2": 0,"THREADS_PER_ROW": 1,"TEXTURE_MEMORY": 0}
    },
    {
      "kernel": "spmv_kernel",
      "time": 1.838,
      "parameters": {"BLOCK_SIZE": 127,"PRECISION": 32,"FORMAT": 2,"UNROLL_LOOP_1": 0,"UNROLL_LOOP_2": 0,"THREADS_PER_ROW": 1,"TEXTURE_MEMORY": 0}
    },
    {
      "kernel": "spmv_kernel",
      "time": 0.945,
      "parameters": {"BLOCK_SIZE": 12,"PRECISION": 64,"FORMAT": 1,"UNROLL_LOOP_1": 0,"UNROLL_LOOP_2": 0,"THREADS_PER_ROW": 1,"TEXTURE_MEMORY": 0}
    },
    {
      "kernel": "spmv_kernel",
      "time": 0.409,
      "parameters": {"BLOCK_SIZE": 848,"PRECISION": 32,"FORMAT": 0,"UNROLL_LOOP_1": 0,"UNROLL_LOOP_2": 0,"THREADS_PER_ROW": 1,"TEXTURE_MEMORY": 0}
    },
    {
      "kernel": "spmv_kernel",
      "time": 1.903,
      "parameters": {"BLOCK_SIZE": 49,"PRECISION": 32,"FORMAT": 2,"UNROLL_LOOP_1": 0,"UNROLL_LOOP_2": 0,"THREADS_PER_ROW": 1,"TEXTURE_MEMORY": 0}
    },
    {
      "kernel": "spmv_kernel",
      "time": 0.348,
      "parameters": {"BLOCK_SIZE": 689,"PRECISION": 32,"FORMAT": 0,"UNROLL_LOOP_1": 1,"UNROLL_LOOP_2": 0,"THREADS_PER_ROW": 1,"TEXTURE_MEMORY": 0}
    },
    {
      "kernel": "spmv_kernel",
      "time": 0.357,
      "parameters": {"BLOCK_SIZE": 733,"PRECISION": 32,"FORMAT": 0,"UNROLL_LOOP_1": 1,"UNROLL_LOOP_2": 0,"THREADS_PER_ROW": 1,"TEXTURE_MEMORY": 0}
    },
    {
      "kernel": "spmv_kernel",
      "time": 0.534,
      "parameters": {"BLOCK_SIZE": 971,"PRECISION": 64,"FORMAT": 0,"UNROLL_LOOP_1": 0,"UNROLL_LOOP_2": 0,"THREADS_PER_ROW": 1,"TEXTURE_MEMORY": 0}
    },
    {
      "kernel": "spmv_kernel",
      "time": 2.084,
      "parameters": {"BLOCK_SIZE": 855,"PRECISION": 64,"FORMAT": 1,"UNROLL_LOOP_1": 0,"UNROLL_LOOP_2": 0,"THREADS_PER_ROW": 1,"TEXTURE_MEMORY": 0}
    },
    {
      "kernel": "spmv_kernel",
      "time": 0.392,
      "parameters": {"BLOCK_SIZE": 215,"PRECISION": 64,"FORMAT": 0,"UNROLL_LOOP_1": 0,"UNROLL_LOOP_2": 0,"THREADS_PER_ROW": 1,"TEXTURE_MEMORY": 0}
    },
    {
      "kernel": "spmv_kernel",
      "time": 2.033,
      "parameters": {"BLOCK_SIZE": 34,"PRECISION": 64,"FORMAT": 1,"UNROLL_LOOP_1": 0,"UNROLL_LOOP_2": 0,"THREADS_PER_ROW": 1,"TEXTURE_MEMORY": 0}
    },
    {
      "kernel": "spmv_kernel",
      "time": 0.394,
      "parameters": {"BLOCK_SIZE": 560,"PRECISION": 32,"FORMAT": 0,"UNROLL_LOOP_1": 0,"UNROLL_LOOP_2": 0,"THREADS_PER_ROW": 1,"TEXTURE_MEMORY": 0}
    },
    {
      "kernel": "spmv_kernel",
      "time": 1.843,
      "parameters": {"BLOCK_SIZE": 31,"PRECISION": 32,"FORMAT": 2,"UNROLL_LOOP_1": 0,"UNROLL_LOOP_2": 0,"THREADS_PER_ROW": 1,"TEXTURE_MEMORY": 0}
    },
    {
      "kernel": "spmv_kernel",
      "time": 0.666,
      "parameters": {"BLOCK_SIZE": 156,"PRECISION": 32,"FORMAT": 2,"UNROLL_LOOP_1": 1,"UNROLL_LOOP_2": 0,"THREADS_PER_ROW": 1,"TEXTURE_MEMORY": 0}
    },
    {
      "kernel": "spmv_kernel",
      "time": 0.350,
      "parameters": {"BLOCK_SIZE": 567,"PRECISION": 64,"FORMAT": 0,"UNROLL_LOOP_1": 1,"UNROLL_LOOP_2": 0,"THREADS_PER_ROW": 1,"TEXTURE_MEMORY": 0}
    },
    {
      "kernel": "spmv_kernel",
      "time": 0.702,
      "parameters": {"BLOCK_SIZE": 235,"PRECISION": 64,"FORMAT": 2,"UNROLL_LOOP_1": 1,"UNROLL_LOOP_2": 0,"THREADS_PER_ROW": 1,"TEXTURE_MEMORY": 0}
    },
    {
      "kernel": "spmv_kernel",
      "time": 0.722,
      "parameters": {"BLOCK_SIZE": 28,"PRECISION": 32,"FORMAT": 2,"UNROLL_LOOP_1": 1,"UNROLL_LOOP_2": 0,"THREADS_PER_ROW": 1,"TEXTURE_MEMORY": 0}
    },
    {
      "kernel": "spmv_kernel",
      "time": 1.003,
      "parameters": {"BLOCK_SIZE": 167,"PRECISION": 64,"FORMAT": 1,"UNROLL_LOOP_1": 1,"UNROLL_LOOP_2": 0,"THREADS_PER_ROW": 1,"TEXTURE_MEMORY": 0}
    },
    {
      "kernel": "spmv_kernel",
      "time": 0.796,
      "parameters": {"BLOCK_SIZE": 50,"PRECISION": 32,"FORMAT": 1,"UNROLL_LOOP_1": 1,"UNROLL_LOOP_2": 0,"THREADS_PER_ROW": 1,"TEXTURE_MEMORY": 0}
    },
    {
      "kernel": "spmv_kernel",
      "time": 2.038,
      "parameters": {"BLOCK_SIZE": 459,"PRECISION": 64,"FORMAT": 1,"UNROLL_LOOP_1": 0,"UNROLL_LOOP_2": 0,"THREADS_PER_ROW": 1,"TEXTURE_MEMORY": 0}
    },
    {
      "kernel": "spmv_kernel",
      "time": 0.781,
      "parameters": {"BLOCK_SIZE": 452,"PRECISION": 64,"FORMAT": 2,"UNROLL_LOOP_1": 1,"UNROLL_LOOP_2": 0,"THREADS_PER_ROW": 1,"TEXTURE_MEMORY": 0}
    },
    {
      "kernel": "spmv_kernel",
      "time": 0.368,
      "parameters": {"BLOCK_SIZE": 293,"PRECISION": 64,"FORMAT": 0,"UNROLL_LOOP_1": 1,"UNROLL_LOOP_2": 0,"THREADS_PER_ROW": 1,"TEXTURE_MEMORY": 0}
    },
    {
      "kernel": "spmv_kernel",
      "time": 0.672,
      "parameters": {"BLOCK_SIZE": 541,"PRECISION": 64,"FORMAT": 2,"UNROLL_LOOP_1": 1,"UNROLL_LOOP_2": 0,"THREADS_PER_ROW": 1,"TEXTURE_MEMORY": 0}
    },
    {
      "kernel": "spmv_kernel",
      "time": 1.747,
      "parameters": {"BLOCK_SIZE": 624,"PRECISION": 32,"FORMAT": 2,"UNROLL_LOOP_1": 0,"UNROLL_LOOP_2": 0,"THREADS_PER_ROW": 1,"TEXTURE_MEMORY": 0}
    },
    {
      "kernel": "spmv_kernel",
      "time": 0.386,
      "parameters": {"BLOCK_SIZE": 452,"PRECISION": 64,"FORMAT": 0,"UNROLL_LOOP_1": 0,"UNROLL_LOOP_2": 0,"THREADS_PER_ROW": 1,"TEXTURE_MEMORY": 0}
    },
    {
      "kernel": "spmv_kernel",
      "time": 0.332,
      "parameters": {"BLOCK_SIZE": 262,"PRECISION": 64,"FORMAT": 0,"UNROLL_LOOP_1": 1,"UNROLL_LOOP_2": 0,"THREADS_PER_ROW": 1,"TEXTURE_MEMORY": 0}
    },
    {
      "kernel": "spmv_kernel",
      "time": 0.384,
      "parameters": {"BLOCK_SIZE": 836,"PRECISION": 32,"FORMAT": 0,"UNROLL_LOOP_1": 1,"UNROLL_LOOP_2": 0,"THREADS_PER_ROW": 1,"TEXTURE_MEMORY": 0}
    },
    {
      "kernel": "spmv_kernel",
      "time": 0.359,
      "parameters": {"BLOCK_SIZE": 61,"PRECISION": 32,"FORMAT": 0,"UNROLL_LOOP_1": 1,"UNROLL_LOOP_2": 0,"THREADS_PER_ROW": 1,"TEXTURE_MEMORY": 0}
    },
    {
      "kernel": "spmv_kernel",
      "time": 1.897,
      "parameters": {"BLOCK_SIZE": 135,"PRECISION": 32,"FORMAT": 2,"UNROLL_LOOP_1": 0,"UNROLL_LOOP_2": 0,"THREADS_PER_ROW": 1,"TEXTURE_MEMORY": 0}
    },
    {
      "kernel": "spmv_kernel",
      "time": 2.041,
      "parameters": {"BLOCK_SIZE": 957,"PRECISION": 32,"FORMAT": 2,"UNROLL_LOOP_1": 0,"UNROLL_LOOP_2": 0,"THREADS_PER_ROW": 1,"TEXTURE_MEMORY": 0}
    },
    {
      "kernel": "spmv_kernel",
      "time": 2.035,
      "parameters": {"BLOCK_SIZE": 977,"PRECISION": 32,"FORMAT": 1,"UNROLL_LOOP_1": 0,"UNROLL_LOOP_2": 0,"THREADS_PER_ROW": 1,"TEXTURE_MEMORY": 0}
    },
    {
      "kernel": "spmv_kernel",
      "time": 1.871,
      "parameters": {"BLOCK_SIZE": 921,"PRECISION": 32,"FORMAT": 1,"UNROLL_LOOP_1": 0,"UNROLL_LOOP_2": 0,"THREADS_PER_ROW": 1,"TEXTURE_MEMORY": 0}
    },
    {
      "kernel": "spmv_kernel",
      "time": 0.778,
      "parameters": {"BLOCK_SIZE": 749,"PRECISION": 32,"FORMAT": 2,"UNROLL_LOOP_1": 1,"UNROLL_LOOP_2": 0,"THREADS_PER_ROW": 1,"TEXTURE_MEMORY": 0}
    },
    {
      "kernel": "spmv_kernel",
      "time": 1.892,
      "parameters": {"BLOCK_SIZE": 194,"PRECISION": 32,"FORMAT": 2,"UNROLL_LOOP_1": 0,"UNROLL_LOOP_2": 0,"THREADS_PER_ROW": 1,"TEXTURE_MEMORY": 0}
    },
    {
      "kernel": "spmv_kernel",
      "time": 0.946,
      "parameters": {"BLOCK_SIZE": 556,"PRECISION": 64,"FORMAT": 1,"UNROLL_LOOP_1": 1,"UNROLL_LOOP_2": 0,"THREADS_PER_ROW": 1,"TEXTURE_MEMORY": 0}
    },
    {
      "kernel": "spmv_kernel",
      "time": 0.895,
      "parameters": {"BLOCK_SIZE": 878,"PRECISION": 32,"FORMAT": 2,"UNROLL_LOOP_1": 1,"UNROLL_LOOP_2": 0,"THREADS_PER_ROW": 1,"TEXTURE_MEMORY": 0}
    },
    {
      "kernel": "spmv_kernel",
      "time": 1.174,
      "parameters": {"BLOCK_SIZE": 855,"PRECISION": 64,"FORMAT": 1,"UNROLL_LOOP_1": 1,"UNROLL_LOOP_2": 0,"THREADS_PER_ROW": 1,"TEXTURE_MEMORY": 0}
    },
    {
      "kernel": "spmv_kernel",
      "time": 1.766,
      "parameters": {"BLOCK_SIZE": 75,"PRECISION": 32,"FORMAT": 1,"UNROLL_LOOP_1": 0,"UNROLL_LOOP_2": 0,"THREADS_PER_ROW": 1,"TEXTURE_MEMORY": 0}
    },
    {
      "kernel": "spmv_kernel",
      "time": 0.683,
      "parameters": {"BLOCK_SIZE": 54,"PRECISION": 32,"FORMAT": 2,"UNROLL_LOOP_1": 1,"UNROLL_LOOP_2": 0,"THREADS_PER_ROW": 1,"TEXTURE_MEMORY": 0}
    },
    {
      "kernel": "spmv_kernel",
      "time": 1.845,
      "parameters": {"BLOCK_SIZE": 157,"PRECISION": 32,"FORMAT": 2,"UNROLL_LOOP_1": 0,"UNROLL_LOOP_2": 0,"THREADS_PER_ROW": 1,"TEXTURE_MEMORY": 0}
    },
    {
      "kernel": "spmv_kernel",
      "time": 0.353,
      "parameters": {"BLOCK_SIZE": 699,"PRECISION": 32,"FORMAT": 0,"UNROLL_LOOP_1": 1,"UNROLL_LOOP_2": 0,"THREADS_PER_ROW": 1,"TEXTURE_MEMORY": 0}
    },
    {
      "kernel": "spmv_kernel",
      "time": 0.371,
      "parameters": {"BLOCK_SIZE": 81,"PRECISION": 32,"FORMAT": 0,"UNROLL_LOOP_1": 1,"UNROLL_LOOP_2": 0,"THREADS_PER_ROW": 1,"TEXTURE_MEMORY": 0}
    },
    {
      "kernel": "spmv_kernel",
      "time": 1.063,
      "parameters": {"BLOCK_SIZE": 757,"PRECISION": 64,"FORMAT": 1,"UNROLL_LOOP_1": 1,"UNROLL_LOOP_2": 0,"THREADS_PER_ROW": 1,"TEXTURE_MEMORY": 0}
    },
    {
      "kernel": "spmv_kernel",
      "time": 0.737,
      "parameters": {"BLOCK_SIZE": 437,"PRECISION": 32,"FORMAT": 2,"UNROLL_LOOP_1": 1,"UNROLL_LOOP_2": 0,"THREADS_PER_ROW": 1,"TEXTURE_MEMORY": 0}
    },
    {
      "kernel": "spmv_kernel",
      "time": 1.741,
      "parameters": {"BLOCK_SIZE": 419,"PRECISION": 32,"FORMAT": 2,"UNROLL_LOOP_1": 0,"UNROLL_LOOP_2": 0,"THREADS_PER_ROW": 1,"TEXTURE_MEMORY": 0}
    }
  ]
}
