{
  "sample": "triad_helper",
  "device": "Tesla T4",
  "platform_version": "CUDA driver 10020",
  "device_vendor": "NVIDIA Corporation",
  "device_type": "GPU",
  "device_core_clock": "1590",
  "device_compute_units": "40",
  "device_extra_info": "SM 7.5",
  "results": [
    {
      "kernel": "triad_helper",
      "time": 0.029,
      "parameters": {"BLOCK_SIZE": 661,"WORK_PER_THREAD": 2,"LOOP_UNROLL_TRIAD": 0,"PRECISION": 32}
    },
    {
      "kernel": "triad_helper",
      "time": 0.035,
      "parameters": {"BLOCK_SIZE": 159,"WORK_PER_THREAD": 2,"LOOP_UNROLL_TRIAD": 0,"PRECISION": 32}
    },
    {
      "kernel": "triad_helper",
      "time": 0.035,
      "parameters": {"BLOCK_SIZE": 784,"WORK_PER_THREAD": 2,"LOOP_UNROLL_TRIAD": 1,"PRECISION": 32}
    },
    {
      "kernel": "triad_helper",
      "time": 0.034,
      "parameters": {"BLOCK_SIZE": 784,"WORK_PER_THREAD": 6,"LOOP_UNROLL_TRIAD": 1,"PRECISION": 32}
    },
    {
      "kernel": "triad_helper",
      "time": 0.034,
      "parameters": {"BLOCK_SIZE": 661,"WORK_PER_THREAD": 2,"LOOP_UNROLL_TRIAD": 1,"PRECISION": 32}
    },
    {
      "kernel": "triad_helper",
      "time": 0.025,
      "parameters": {"BLOCK_SIZE": 661,"WORK_PER_THREAD": 2,"LOOP_UNROLL_TRIAD": 1,"PRECISION": 32}
    },
    {
      "kernel": "triad_helper",
      "time": 0.025,
      "parameters": {"BLOCK_SIZE": 661,"WORK_PER_THREAD": 2,"LOOP_UNROLL_TRIAD": 0,"PRECISION": 32}
    },
    {
      "kernel": "triad_helper",
      "time": 0.024,
      "parameters": {"BLOCK_SIZE": 661,"WORK_PER_THREAD": 2,"LOOP_UNROLL_TRIAD": 1,"PRECISION": 32}
    },
    {
      "kernel": "triad_helper",
      "time": 0.024,
      "parameters": {"BLOCK_SIZE": 661,"WORK_PER_THREAD": 2,"LOOP_UNROLL_TRIAD": 1,"PRECISION": 32}
    },
    {
      "kernel": "triad_helper",
      "time": 0.024,
      "parameters": {"BLOCK_SIZE": 661,"WORK_PER_THREAD": 2,"LOOP_UNROLL_TRIAD": 1,"PRECISION": 32}
    },
    {
      "kernel": "triad_helper",
      "time": 0.034,
      "parameters": {"BLOCK_SIZE": 661,"WORK_PER_THREAD": 2,"LOOP_UNROLL_TRIAD": 1,"PRECISION": 64}
    },
    {
      "kernel": "triad_helper",
      "time": 0.044,
      "parameters": {"BLOCK_SIZE": 661,"WORK_PER_THREAD": 5,"LOOP_UNROLL_TRIAD": 0,"PRECISION": 64}
    },
    {
      "kernel": "triad_helper",
      "time": 0.029,
      "parameters": {"BLOCK_SIZE": 661,"WORK_PER_THREAD": 5,"LOOP_UNROLL_TRIAD": 0,"PRECISION": 32}
    },
    {
      "kernel": "triad_helper",
      "time": 0.024,
      "parameters": {"BLOCK_SIZE": 661,"WORK_PER_THREAD": 2,"LOOP_UNROLL_TRIAD": 1,"PRECISION": 32}
    },
    {
      "kernel": "triad_helper",
      "time": 0.026,
      "parameters": {"BLOCK_SIZE": 661,"WORK_PER_THREAD": 2,"LOOP_UNROLL_TRIAD": 1,"PRECISION": 32}
    },
    {
      "kernel": "triad_helper",
      "time": 0.024,
      "parameters": {"BLOCK_SIZE": 661,"WORK_PER_THREAD": 2,"LOOP_UNROLL_TRIAD": 1,"PRECISION": 32}
    },
    {
      "kernel": "triad_helper",
      "time": 0.024,
      "parameters": {"BLOCK_SIZE": 661,"WORK_PER_THREAD": 2,"LOOP_UNROLL_TRIAD": 1,"PRECISION": 32}
    },
    {
      "kernel": "triad_helper",
      "time": 0.023,
      "parameters": {"BLOCK_SIZE": 214,"WORK_PER_THREAD": 2,"LOOP_UNROLL_TRIAD": 1,"PRECISION": 32}
    },
    {
      "kernel": "triad_helper",
      "time": 0.023,
      "parameters": {"BLOCK_SIZE": 214,"WORK_PER_THREAD": 2,"LOOP_UNROLL_TRIAD": 1,"PRECISION": 32}
    },
    {
      "kernel": "triad_helper",
      "time": 0.034,
      "parameters": {"BLOCK_SIZE": 214,"WORK_PER_THREAD": 8,"LOOP_UNROLL_TRIAD": 1,"PRECISION": 32}
    },
    {
      "kernel": "triad_helper",
      "time": 0.035,
      "parameters": {"BLOCK_SIZE": 214,"WORK_PER_THREAD": 8,"LOOP_UNROLL_TRIAD": 1,"PRECISION": 32}
    },
    {
      "kernel": "triad_helper",
      "time": 0.024,
      "parameters": {"BLOCK_SIZE": 214,"WORK_PER_THREAD": 2,"LOOP_UNROLL_TRIAD": 1,"PRECISION": 32}
    },
    {
      "kernel": "triad_helper",
      "time": 0.038,
      "parameters": {"BLOCK_SIZE": 975,"WORK_PER_THREAD": 7,"LOOP_UNROLL_TRIAD": 1,"PRECISION": 32}
    },
    {
      "kernel": "triad_helper",
      "time": 0.023,
      "parameters": {"BLOCK_SIZE": 214,"WORK_PER_THREAD": 2,"LOOP_UNROLL_TRIAD": 1,"PRECISION": 32}
    },
    {
      "kernel": "triad_helper",
      "time": 0.024,
      "parameters": {"BLOCK_SIZE": 793,"WORK_PER_THREAD": 2,"LOOP_UNROLL_TRIAD": 1,"PRECISION": 32}
    },
    {
      "kernel": "triad_helper",
      "time": 0.024,
      "parameters": {"BLOCK_SIZE": 214,"WORK_PER_THREAD": 2,"LOOP_UNROLL_TRIAD": 1,"PRECISION": 32}
    },
    {
      "kernel": "triad_helper",
      "time": 0.023,
      "parameters": {"BLOCK_SIZE": 214,"WORK_PER_THREAD": 2,"LOOP_UNROLL_TRIAD": 1,"PRECISION": 32}
    },
    {
      "kernel": "triad_helper",
      "time": 0.024,
      "parameters": {"BLOCK_SIZE": 363,"WORK_PER_THREAD": 2,"LOOP_UNROLL_TRIAD": 1,"PRECISION": 32}
    },
    {
      "kernel": "triad_helper",
      "time": 0.039,
      "parameters": {"BLOCK_SIZE": 363,"WORK_PER_THREAD": 8,"LOOP_UNROLL_TRIAD": 1,"PRECISION": 32}
    },
    {
      "kernel": "triad_helper",
      "time": 0.026,
      "parameters": {"BLOCK_SIZE": 214,"WORK_PER_THREAD": 2,"LOOP_UNROLL_TRIAD": 1,"PRECISION": 32}
    },
    {
      "kernel": "triad_helper",
      "time": 0.034,
      "parameters": {"BLOCK_SIZE": 214,"WORK_PER_THREAD": 2,"LOOP_UNROLL_TRIAD": 1,"PRECISION": 32}
    },
    {
      "kernel": "triad_helper",
      "time": 0.024,
      "parameters": {"BLOCK_SIZE": 214,"WORK_PER_THREAD": 2,"LOOP_UNROLL_TRIAD": 1,"PRECISION": 32}
    },
    {
      "kernel": "triad_helper",
      "time": 0.025,
      "parameters": {"BLOCK_SIZE": 695,"WORK_PER_THREAD": 2,"LOOP_UNROLL_TRIAD": 1,"PRECISION": 32}
    },
    {
      "kernel": "triad_helper",
      "time": 0.025,
      "parameters": {"BLOCK_SIZE": 695,"WORK_PER_THREAD": 2,"LOOP_UNROLL_TRIAD": 1,"PRECISION": 32}
    },
    {
      "kernel": "triad_helper",
      "time": 0.029,
      "parameters": {"BLOCK_SIZE": 714,"WORK_PER_THREAD": 5,"LOOP_UNROLL_TRIAD": 0,"PRECISION": 32}
    },
    {
      "kernel": "triad_helper",
      "time": 0.024,
      "parameters": {"BLOCK_SIZE": 214,"WORK_PER_THREAD": 2,"LOOP_UNROLL_TRIAD": 1,"PRECISION": 32}
    },
    {
      "kernel": "triad_helper",
      "time": 0.024,
      "parameters": {"BLOCK_SIZE": 630,"WORK_PER_THREAD": 2,"LOOP_UNROLL_TRIAD": 0,"PRECISION": 32}
    },
    {
      "kernel": "triad_helper",
      "time": 0.024,
      "parameters": {"BLOCK_SIZE": 214,"WORK_PER_THREAD": 2,"LOOP_UNROLL_TRIAD": 1,"PRECISION": 32}
    },
    {
      "kernel": "triad_helper",
      "time": 0.032,
      "parameters": {"BLOCK_SIZE": 115,"WORK_PER_THREAD": 2,"LOOP_UNROLL_TRIAD": 1,"PRECISION": 64}
    },
    {
      "kernel": "triad_helper",
      "time": 0.024,
      "parameters": {"BLOCK_SIZE": 115,"WORK_PER_THREAD": 2,"LOOP_UNROLL_TRIAD": 1,"PRECISION": 32}
    },
    {
      "kernel": "triad_helper",
      "time": 0.024,
      "parameters": {"BLOCK_SIZE": 928,"WORK_PER_THREAD": 2,"LOOP_UNROLL_TRIAD": 1,"PRECISION": 32}
    },
    {
      "kernel": "triad_helper",
      "time": 0.033,
      "parameters": {"BLOCK_SIZE": 928,"WORK_PER_THREAD": 2,"LOOP_UNROLL_TRIAD": 1,"PRECISION": 64}
    },
    {
      "kernel": "triad_helper",
      "time": 0.034,
      "parameters": {"BLOCK_SIZE": 928,"WORK_PER_THREAD": 2,"LOOP_UNROLL_TRIAD": 1,"PRECISION": 64}
    },
    {
      "kernel": "triad_helper",
      "time": 0.024,
      "parameters": {"BLOCK_SIZE": 214,"WORK_PER_THREAD": 2,"LOOP_UNROLL_TRIAD": 1,"PRECISION": 32}
    },
    {
      "kernel": "triad_helper",
      "time": 0.037,
      "parameters": {"BLOCK_SIZE": 868,"WORK_PER_THREAD": 6,"LOOP_UNROLL_TRIAD": 1,"PRECISION": 32}
    },
    {
      "kernel": "triad_helper",
      "time": 0.031,
      "parameters": {"BLOCK_SIZE": 209,"WORK_PER_THREAD": 6,"LOOP_UNROLL_TRIAD": 1,"PRECISION": 32}
    },
    {
      "kernel": "triad_helper",
      "time": 0.024,
      "parameters": {"BLOCK_SIZE": 209,"WORK_PER_THREAD": 2,"LOOP_UNROLL_TRIAD": 1,"PRECISION": 32}
    },
    {
      "kernel": "triad_helper",
      "time": 0.033,
      "parameters": {"BLOCK_SIZE": 214,"WORK_PER_THREAD": 7,"LOOP_UNROLL_TRIAD": 1,"PRECISION": 32}
    },
    {
      "kernel": "triad_helper",
      "time": 0.024,
      "parameters": {"BLOCK_SIZE": 845,"WORK_PER_THREAD": 2,"LOOP_UNROLL_TRIAD": 1,"PRECISION": 32}
    },
    {
      "kernel": "triad_helper",
      "time": 0.024,
      "parameters": {"BLOCK_SIZE": 845,"WORK_PER_THREAD": 2,"LOOP_UNROLL_TRIAD": 1,"PRECISION": 32}
    },
    {
      "kernel": "triad_helper",
      "time": 0.037,
      "parameters": {"BLOCK_SIZE": 845,"WORK_PER_THREAD": 6,"LOOP_UNROLL_TRIAD": 1,"PRECISION": 32}
    },
    {
      "kernel": "triad_helper",
      "time": 0.032,
      "parameters": {"BLOCK_SIZE": 214,"WORK_PER_THREAD": 6,"LOOP_UNROLL_TRIAD": 1,"PRECISION": 32}
    },
    {
      "kernel": "triad_helper",
      "time": 0.024,
      "parameters": {"BLOCK_SIZE": 214,"WORK_PER_THREAD": 2,"LOOP_UNROLL_TRIAD": 1,"PRECISION": 32}
    },
    {
      "kernel": "triad_helper",
      "time": 0.023,
      "parameters": {"BLOCK_SIZE": 214,"WORK_PER_THREAD": 2,"LOOP_UNROLL_TRIAD": 0,"PRECISION": 32}
    },
    {
      "kernel": "triad_helper",
      "time": 0.025,
      "parameters": {"BLOCK_SIZE": 214,"WORK_PER_THREAD": 2,"LOOP_UNROLL_TRIAD": 0,"PRECISION": 32}
    },
    {
      "kernel": "triad_helper",
      "time": 0.024,
      "parameters": {"BLOCK_SIZE": 214,"WORK_PER_THREAD": 2,"LOOP_UNROLL_TRIAD": 0,"PRECISION": 32}
    },
    {
      "kernel": "triad_helper",
      "time": 0.024,
      "parameters": {"BLOCK_SIZE": 1001,"WORK_PER_THREAD": 2,"LOOP_UNROLL_TRIAD": 0,"PRECISION": 32}
    },
    {
      "kernel": "triad_helper",
      "time": 0.028,
      "parameters": {"BLOCK_SIZE": 214,"WORK_PER_THREAD": 2,"LOOP_UNROLL_TRIAD": 0,"PRECISION": 32}
    },
    {
      "kernel": "triad_helper",
      "time": 0.034,
      "parameters": {"BLOCK_SIZE": 916,"WORK_PER_THREAD": 2,"LOOP_UNROLL_TRIAD": 0,"PRECISION": 64}
    },
    {
      "kernel": "triad_helper",
      "time": 0.035,
      "parameters": {"BLOCK_SIZE": 214,"WORK_PER_THREAD": 2,"LOOP_UNROLL_TRIAD": 1,"PRECISION": 32}
    },
    {
      "kernel": "triad_helper",
      "time": 0.039,
      "parameters": {"BLOCK_SIZE": 214,"WORK_PER_THREAD": 10,"LOOP_UNROLL_TRIAD": 1,"PRECISION": 32}
    },
    {
      "kernel": "triad_helper",
      "time": 0.039,
      "parameters": {"BLOCK_SIZE": 214,"WORK_PER_THREAD": 10,"LOOP_UNROLL_TRIAD": 1,"PRECISION": 32}
    },
    {
      "kernel": "triad_helper",
      "time": 0.023,
      "parameters": {"BLOCK_SIZE": 288,"WORK_PER_THREAD": 2,"LOOP_UNROLL_TRIAD": 1,"PRECISION": 32}
    },
    {
      "kernel": "triad_helper",
      "time": 0.031,
      "parameters": {"BLOCK_SIZE": 214,"WORK_PER_THREAD": 2,"LOOP_UNROLL_TRIAD": 1,"PRECISION": 64}
    },
    {
      "kernel": "triad_helper",
      "time": 0.024,
      "parameters": {"BLOCK_SIZE": 214,"WORK_PER_THREAD": 2,"LOOP_UNROLL_TRIAD": 1,"PRECISION": 32}
    },
    {
      "kernel": "triad_helper",
      "time": 0.023,
      "parameters": {"BLOCK_SIZE": 74,"WORK_PER_THREAD": 2,"LOOP_UNROLL_TRIAD": 1,"PRECISION": 32}
    },
    {
      "kernel": "triad_helper",
      "time": 0.024,
      "parameters": {"BLOCK_SIZE": 74,"WORK_PER_THREAD": 2,"LOOP_UNROLL_TRIAD": 1,"PRECISION": 32}
    },
    {
      "kernel": "triad_helper",
      "time": 0.025,
      "parameters": {"BLOCK_SIZE": 449,"WORK_PER_THREAD": 2,"LOOP_UNROLL_TRIAD": 1,"PRECISION": 32}
    },
    {
      "kernel": "triad_helper",
      "time": 0.023,
      "parameters": {"BLOCK_SIZE": 449,"WORK_PER_THREAD": 2,"LOOP_UNROLL_TRIAD": 1,"PRECISION": 32}
    },
    {
      "kernel": "triad_helper",
      "time": 0.025,
      "parameters": {"BLOCK_SIZE": 74,"WORK_PER_THREAD": 2,"LOOP_UNROLL_TRIAD": 1,"PRECISION": 32}
    },
    {
      "kernel": "triad_helper",
      "time": 0.024,
      "parameters": {"BLOCK_SIZE": 74,"WORK_PER_THREAD": 2,"LOOP_UNROLL_TRIAD": 1,"PRECISION": 32}
    },
    {
      "kernel": "triad_helper",
      "time": 0.023,
      "parameters": {"BLOCK_SIZE": 391,"WORK_PER_THREAD": 2,"LOOP_UNROLL_TRIAD": 1,"PRECISION": 32}
    },
    {
      "kernel": "triad_helper",
      "time": 0.024,
      "parameters": {"BLOCK_SIZE": 74,"WORK_PER_THREAD": 2,"LOOP_UNROLL_TRIAD": 1,"PRECISION": 32}
    },
    {
      "kernel": "triad_helper",
      "time": 0.030,
      "parameters": {"BLOCK_SIZE": 74,"WORK_PER_THREAD": 2,"LOOP_UNROLL_TRIAD": 1,"PRECISION": 64}
    },
    {
      "kernel": "triad_helper",
      "time": 0.024,
      "parameters": {"BLOCK_SIZE": 74,"WORK_PER_THREAD": 2,"LOOP_UNROLL_TRIAD": 0,"PRECISION": 32}
    },
    {
      "kernel": "triad_helper",
      "time": 0.024,
      "parameters": {"BLOCK_SIZE": 74,"WORK_PER_THREAD": 2,"LOOP_UNROLL_TRIAD": 0,"PRECISION": 32}
    },
    {
      "kernel": "triad_helper",
      "time": 0.024,
      "parameters": {"BLOCK_SIZE": 74,"WORK_PER_THREAD": 2,"LOOP_UNROLL_TRIAD": 0,"PRECISION": 32}
    },
    {
      "kernel": "triad_helper",
      "time": 0.036,
      "parameters": {"BLOCK_SIZE": 74,"WORK_PER_THREAD": 9,"LOOP_UNROLL_TRIAD": 1,"PRECISION": 32}
    },
    {
      "kernel": "triad_helper",
      "time": 0.035,
      "parameters": {"BLOCK_SIZE": 74,"WORK_PER_THREAD": 9,"LOOP_UNROLL_TRIAD": 1,"PRECISION": 32}
    },
    {
      "kernel": "triad_helper",
      "time": 0.024,
      "parameters": {"BLOCK_SIZE": 589,"WORK_PER_THREAD": 2,"LOOP_UNROLL_TRIAD": 1,"PRECISION": 32}
    },
    {
      "kernel": "triad_helper",
      "time": 0.025,
      "parameters": {"BLOCK_SIZE": 1019,"WORK_PER_THREAD": 2,"LOOP_UNROLL_TRIAD": 1,"PRECISION": 32}
    },
    {
      "kernel": "triad_helper",
      "time": 0.024,
      "parameters": {"BLOCK_SIZE": 74,"WORK_PER_THREAD": 2,"LOOP_UNROLL_TRIAD": 1,"PRECISION": 32}
    },
    {
      "kernel": "triad_helper",
      "time": 0.024,
      "parameters": {"BLOCK_SIZE": 74,"WORK_PER_THREAD": 2,"LOOP_UNROLL_TRIAD": 1,"PRECISION": 32}
    },
    {
      "kernel": "triad_helper",
      "time": 0.024,
      "parameters": {"BLOCK_SIZE": 896,"WORK_PER_THREAD": 2,"LOOP_UNROLL_TRIAD": 0,"PRECISION": 32}
    },
    {
      "kernel": "triad_helper",
      "time": 0.025,
      "parameters": {"BLOCK_SIZE": 329,"WORK_PER_THREAD": 2,"LOOP_UNROLL_TRIAD": 1,"PRECISION": 32}
    },
    {
      "kernel": "triad_helper",
      "time": 0.036,
      "parameters": {"BLOCK_SIZE": 424,"WORK_PER_THREAD": 2,"LOOP_UNROLL_TRIAD": 1,"PRECISION": 64}
    },
    {
      "kernel": "triad_helper",
      "time": 0.028,
      "parameters": {"BLOCK_SIZE": 424,"WORK_PER_THREAD": 2,"LOOP_UNROLL_TRIAD": 1,"PRECISION": 32}
    },
    {
      "kernel": "triad_helper",
      "time": 0.024,
      "parameters": {"BLOCK_SIZE": 74,"WORK_PER_THREAD": 2,"LOOP_UNROLL_TRIAD": 1,"PRECISION": 32}
    },
    {
      "kernel": "triad_helper",
      "time": 0.024,
      "parameters": {"BLOCK_SIZE": 74,"WORK_PER_THREAD": 2,"LOOP_UNROLL_TRIAD": 0,"PRECISION": 32}
    },
    {
      "kernel": "triad_helper",
      "time": 0.024,
      "parameters": {"BLOCK_SIZE": 74,"WORK_PER_THREAD": 2,"LOOP_UNROLL_TRIAD": 0,"PRECISION": 32}
    },
    {
      "kernel": "triad_helper",
      "time": 0.025,
      "parameters": {"BLOCK_SIZE": 74,"WORK_PER_THREAD": 2,"LOOP_UNROLL_TRIAD": 0,"PRECISION": 32}
    },
    {
      "kernel": "triad_helper",
      "time": 0.023,
      "parameters": {"BLOCK_SIZE": 74,"WORK_PER_THREAD": 2,"LOOP_UNROLL_TRIAD": 0,"PRECISION": 32}
    },
    {
      "kernel": "triad_helper",
      "time": 0.025,
      "parameters": {"BLOCK_SIZE": 74,"WORK_PER_THREAD": 2,"LOOP_UNROLL_TRIAD": 0,"PRECISION": 32}
    },
    {
      "kernel": "triad_helper",
      "time": 0.025,
      "parameters": {"BLOCK_SIZE": 676,"WORK_PER_THREAD": 2,"LOOP_UNROLL_TRIAD": 1,"PRECISION": 32}
    },
    {
      "kernel": "triad_helper",
      "time": 0.039,
      "parameters": {"BLOCK_SIZE": 323,"WORK_PER_THREAD": 10,"LOOP_UNROLL_TRIAD": 1,"PRECISION": 32}
    },
    {
      "kernel": "triad_helper",
      "time": 0.033,
      "parameters": {"BLOCK_SIZE": 323,"WORK_PER_THREAD": 7,"LOOP_UNROLL_TRIAD": 1,"PRECISION": 32}
    },
    {
      "kernel": "triad_helper",
      "time": 0.024,
      "parameters": {"BLOCK_SIZE": 74,"WORK_PER_THREAD": 2,"LOOP_UNROLL_TRIAD": 1,"PRECISION": 32}
    },
    {
      "kernel": "triad_helper",
      "time": 0.023,
      "parameters": {"BLOCK_SIZE": 74,"WORK_PER_THREAD": 2,"LOOP_UNROLL_TRIAD": 1,"PRECISION": 32}
    },
    {
      "kernel": "triad_helper",
      "time": 0.024,
      "parameters": {"BLOCK_SIZE": 74,"WORK_PER_THREAD": 2,"LOOP_UNROLL_TRIAD": 1,"PRECISION": 32}
    },
    {
      "kernel": "triad_helper",
      "time": 0.032,
      "parameters": {"BLOCK_SIZE": 74,"WORK_PER_THREAD": 2,"LOOP_UNROLL_TRIAD": 1,"PRECISION": 64}
    },
    {
      "kernel": "triad_helper",
      "time": 0.025,
      "parameters": {"BLOCK_SIZE": 74,"WORK_PER_THREAD": 2,"LOOP_UNROLL_TRIAD": 1,"PRECISION": 32}
    },
    {
      "kernel": "triad_helper",
      "time": 0.034,
      "parameters": {"BLOCK_SIZE": 872,"WORK_PER_THREAD": 2,"LOOP_UNROLL_TRIAD": 1,"PRECISION": 64}
    }
  ]
}
