[
    {
        "parameters": {
            "USE_FAST_MATH": 0,
            "GRID_SIZE": 1,
            "BLOCK_SIZE": 512,
            "MAX_REGISTERS": 120,
            "UNROLL_LOOP_2": 0,
            "UNROLL_LOOP_1": 1,
            "PRECISION": 64,
            "OPTIMIZATION_LEVEL_DEVICE": 1,
            "OPTIMIZATION_LEVEL_HOST": 0,
            "GPUS": 1
        },
        "time": 1.249492883682251
    },
    {
        "parameters": {
            "OPTIMIZATION_LEVEL_DEVICE": 3,
            "USE_FAST_MATH": 0,
            "BLOCK_SIZE": 512,
            "GRID_SIZE": 128,
            "OPTIMIZATION_LEVEL_HOST": 1,
            "MAX_REGISTERS": -1,
            "PRECISION": 32,
            "UNROLL_LOOP_1": 1,
            "UNROLL_LOOP_2": 1,
            "GPUS": 1
        },
        "time": 0.7247829437255859
    },
    {
        "parameters": {
            "OPTIMIZATION_LEVEL_DEVICE": 2,
            "USE_FAST_MATH": 0,
            "BLOCK_SIZE": 256,
            "GRID_SIZE": 256,
            "OPTIMIZATION_LEVEL_HOST": 0,
            "MAX_REGISTERS": 40,
            "PRECISION": 32,
            "UNROLL_LOOP_1": 1,
            "UNROLL_LOOP_2": 0,
            "GPUS": 1
        },
        "time": 0.7535769939422607
    },
    {
        "parameters": {
            "OPTIMIZATION_LEVEL_DEVICE": 1,
            "USE_FAST_MATH": 0,
            "BLOCK_SIZE": 512,
            "GRID_SIZE": 256,
            "OPTIMIZATION_LEVEL_HOST": 0,
            "MAX_REGISTERS": 100,
            "PRECISION": 32,
            "UNROLL_LOOP_1": 0,
            "UNROLL_LOOP_2": 0,
            "GPUS": 1
        },
        "time": 0.8697938919067383
    },
    {
        "parameters": {
            "USE_FAST_MATH": 0,
            "GRID_SIZE": 2,
            "BLOCK_SIZE": 256,
            "MAX_REGISTERS": 100,
            "UNROLL_LOOP_2": 1,
            "UNROLL_LOOP_1": 1,
            "PRECISION": 32,
            "OPTIMIZATION_LEVEL_DEVICE": 0,
            "OPTIMIZATION_LEVEL_HOST": 1,
            "GPUS": 1
        },
        "time": 1.855198860168457
    },
    {
        "parameters": {
            "OPTIMIZATION_LEVEL_DEVICE": 3,
            "USE_FAST_MATH": 0,
            "BLOCK_SIZE": 512,
            "GRID_SIZE": 8,
            "OPTIMIZATION_LEVEL_HOST": 1,
            "MAX_REGISTERS": -1,
            "PRECISION": 32,
            "UNROLL_LOOP_1": 1,
            "UNROLL_LOOP_2": 1,
            "GPUS": 1
        },
        "time": 0.7717621326446533
    },
    {
        "parameters": {
            "USE_FAST_MATH": 0,
            "GRID_SIZE": 16,
            "BLOCK_SIZE": 64,
            "MAX_REGISTERS": 60,
            "UNROLL_LOOP_2": 0,
            "UNROLL_LOOP_1": 0,
            "PRECISION": 64,
            "OPTIMIZATION_LEVEL_DEVICE": 0,
            "OPTIMIZATION_LEVEL_HOST": 2,
            "GPUS": 1
        },
        "time": 1.0814216136932373
    },
    {
        "parameters": {
            "OPTIMIZATION_LEVEL_DEVICE": 3,
            "USE_FAST_MATH": 0,
            "BLOCK_SIZE": 512,
            "GRID_SIZE": 128,
            "OPTIMIZATION_LEVEL_HOST": 1,
            "MAX_REGISTERS": 80,
            "PRECISION": 32,
            "UNROLL_LOOP_1": 1,
            "UNROLL_LOOP_2": 1,
            "GPUS": 1
        },
        "time": 0.7178962230682373
    },
    {
        "parameters": {
            "OPTIMIZATION_LEVEL_DEVICE": 3,
            "USE_FAST_MATH": 0,
            "BLOCK_SIZE": 512,
            "GRID_SIZE": 4,
            "OPTIMIZATION_LEVEL_HOST": 1,
            "MAX_REGISTERS": 80,
            "PRECISION": 32,
            "UNROLL_LOOP_1": 1,
            "UNROLL_LOOP_2": 1,
            "GPUS": 1
        },
        "time": 0.8240768909454346
    },
    {
        "parameters": {
            "OPTIMIZATION_LEVEL_DEVICE": 2,
            "USE_FAST_MATH": 0,
            "BLOCK_SIZE": 512,
            "GRID_SIZE": 128,
            "OPTIMIZATION_LEVEL_HOST": 1,
            "MAX_REGISTERS": 20,
            "PRECISION": 32,
            "UNROLL_LOOP_1": 1,
            "UNROLL_LOOP_2": 1,
            "GPUS": 1
        },
        "time": 0.7327902317047119
    },
    {
        "parameters": {
            "OPTIMIZATION_LEVEL_DEVICE": 3,
            "USE_FAST_MATH": 0,
            "BLOCK_SIZE": 128,
            "GRID_SIZE": 128,
            "OPTIMIZATION_LEVEL_HOST": 1,
            "MAX_REGISTERS": -1,
            "PRECISION": 32,
            "UNROLL_LOOP_1": 1,
            "UNROLL_LOOP_2": 1,
            "GPUS": 1
        },
        "time": 0.7316601276397705
    },
    {
        "parameters": {
            "OPTIMIZATION_LEVEL_DEVICE": 3,
            "USE_FAST_MATH": 0,
            "BLOCK_SIZE": 512,
            "GRID_SIZE": 8,
            "OPTIMIZATION_LEVEL_HOST": 2,
            "MAX_REGISTERS": 80,
            "PRECISION": 32,
            "UNROLL_LOOP_1": 1,
            "UNROLL_LOOP_2": 1,
            "GPUS": 1
        },
        "time": 0.762939453125
    },
    {
        "parameters": {
            "OPTIMIZATION_LEVEL_DEVICE": 3,
            "USE_FAST_MATH": 0,
            "BLOCK_SIZE": 512,
            "GRID_SIZE": 128,
            "OPTIMIZATION_LEVEL_HOST": 1,
            "MAX_REGISTERS": 20,
            "PRECISION": 32,
            "UNROLL_LOOP_1": 1,
            "UNROLL_LOOP_2": 1,
            "GPUS": 1
        },
        "time": 0.7595913410186768
    },
    {
        "parameters": {
            "OPTIMIZATION_LEVEL_DEVICE": 3,
            "USE_FAST_MATH": 0,
            "BLOCK_SIZE": 512,
            "GRID_SIZE": 128,
            "OPTIMIZATION_LEVEL_HOST": 1,
            "MAX_REGISTERS": 80,
            "PRECISION": 64,
            "UNROLL_LOOP_1": 1,
            "UNROLL_LOOP_2": 1,
            "GPUS": 1
        },
        "time": 0.7425074577331543
    },
    {
        "parameters": {
            "USE_FAST_MATH": 0,
            "GRID_SIZE": 1,
            "BLOCK_SIZE": 512,
            "MAX_REGISTERS": 40,
            "UNROLL_LOOP_2": 0,
            "UNROLL_LOOP_1": 0,
            "PRECISION": 64,
            "OPTIMIZATION_LEVEL_DEVICE": 3,
            "OPTIMIZATION_LEVEL_HOST": 2,
            "GPUS": 1
        },
        "time": 1.1758825778961182
    },
    {
        "parameters": {
            "USE_FAST_MATH": 0,
            "GRID_SIZE": 8,
            "BLOCK_SIZE": 512,
            "MAX_REGISTERS": -1,
            "UNROLL_LOOP_2": 1,
            "UNROLL_LOOP_1": 0,
            "PRECISION": 32,
            "OPTIMIZATION_LEVEL_DEVICE": 0,
            "OPTIMIZATION_LEVEL_HOST": 2,
            "GPUS": 1
        },
        "time": 0.9092769622802734
    },
    {
        "parameters": {
            "OPTIMIZATION_LEVEL_DEVICE": 1,
            "USE_FAST_MATH": 1,
            "BLOCK_SIZE": 256,
            "GRID_SIZE": 64,
            "OPTIMIZATION_LEVEL_HOST": 3,
            "MAX_REGISTERS": 40,
            "PRECISION": 64,
            "UNROLL_LOOP_1": 1,
            "UNROLL_LOOP_2": 0,
            "GPUS": 1
        },
        "time": 0.7323079109191895
    },
    {
        "parameters": {
            "OPTIMIZATION_LEVEL_DEVICE": 0,
            "USE_FAST_MATH": 1,
            "BLOCK_SIZE": 256,
            "GRID_SIZE": 1,
            "OPTIMIZATION_LEVEL_HOST": 3,
            "MAX_REGISTERS": 100,
            "PRECISION": 64,
            "UNROLL_LOOP_1": 0,
            "UNROLL_LOOP_2": 1,
            "GPUS": 1
        },
        "time": 2.2747771739959717
    },
    {
        "parameters": {
            "OPTIMIZATION_LEVEL_DEVICE": 3,
            "USE_FAST_MATH": 0,
            "BLOCK_SIZE": 512,
            "GRID_SIZE": 128,
            "OPTIMIZATION_LEVEL_HOST": 1,
            "MAX_REGISTERS": 100,
            "PRECISION": 32,
            "UNROLL_LOOP_1": 1,
            "UNROLL_LOOP_2": 1,
            "GPUS": 1
        },
        "time": 0.7130963802337646
    },
    {
        "parameters": {
            "OPTIMIZATION_LEVEL_DEVICE": 3,
            "USE_FAST_MATH": 0,
            "BLOCK_SIZE": 512,
            "GRID_SIZE": 256,
            "OPTIMIZATION_LEVEL_HOST": 1,
            "MAX_REGISTERS": 80,
            "PRECISION": 32,
            "UNROLL_LOOP_1": 1,
            "UNROLL_LOOP_2": 1,
            "GPUS": 1
        },
        "time": 0.7135665416717529
    },
    {
        "parameters": {
            "OPTIMIZATION_LEVEL_DEVICE": 3,
            "USE_FAST_MATH": 0,
            "BLOCK_SIZE": 128,
            "GRID_SIZE": 128,
            "OPTIMIZATION_LEVEL_HOST": 1,
            "MAX_REGISTERS": 80,
            "PRECISION": 32,
            "UNROLL_LOOP_1": 1,
            "UNROLL_LOOP_2": 1,
            "GPUS": 1
        },
        "time": 0.7216203212738037
    },
    {
        "parameters": {
            "OPTIMIZATION_LEVEL_DEVICE": 3,
            "USE_FAST_MATH": 0,
            "BLOCK_SIZE": 256,
            "GRID_SIZE": 128,
            "OPTIMIZATION_LEVEL_HOST": 1,
            "MAX_REGISTERS": 80,
            "PRECISION": 64,
            "UNROLL_LOOP_1": 1,
            "UNROLL_LOOP_2": 1,
            "GPUS": 1
        },
        "time": 0.7088806629180908
    },
    {
        "parameters": {
            "OPTIMIZATION_LEVEL_DEVICE": 3,
            "USE_FAST_MATH": 0,
            "BLOCK_SIZE": 256,
            "GRID_SIZE": 128,
            "OPTIMIZATION_LEVEL_HOST": 1,
            "MAX_REGISTERS": 60,
            "PRECISION": 64,
            "UNROLL_LOOP_1": 1,
            "UNROLL_LOOP_2": 1,
            "GPUS": 1
        },
        "time": 0.6966652870178223
    },
    {
        "parameters": {
            "OPTIMIZATION_LEVEL_DEVICE": 3,
            "USE_FAST_MATH": 0,
            "BLOCK_SIZE": 256,
            "GRID_SIZE": 128,
            "OPTIMIZATION_LEVEL_HOST": 1,
            "MAX_REGISTERS": 120,
            "PRECISION": 64,
            "UNROLL_LOOP_1": 1,
            "UNROLL_LOOP_2": 1,
            "GPUS": 1
        },
        "time": 0.7242040634155273
    },
    {
        "parameters": {
            "OPTIMIZATION_LEVEL_DEVICE": 3,
            "USE_FAST_MATH": 0,
            "BLOCK_SIZE": 256,
            "GRID_SIZE": 128,
            "OPTIMIZATION_LEVEL_HOST": 1,
            "MAX_REGISTERS": 60,
            "PRECISION": 32,
            "UNROLL_LOOP_1": 1,
            "UNROLL_LOOP_2": 1,
            "GPUS": 1
        },
        "time": 0.748755693435669
    },
    {
        "parameters": {
            "OPTIMIZATION_LEVEL_DEVICE": 3,
            "USE_FAST_MATH": 0,
            "BLOCK_SIZE": 256,
            "GRID_SIZE": 1,
            "OPTIMIZATION_LEVEL_HOST": 1,
            "MAX_REGISTERS": 60,
            "PRECISION": 64,
            "UNROLL_LOOP_1": 1,
            "UNROLL_LOOP_2": 1,
            "GPUS": 1
        },
        "time": 1.1967785358428955
    },
    {
        "parameters": {
            "OPTIMIZATION_LEVEL_DEVICE": 3,
            "USE_FAST_MATH": 0,
            "BLOCK_SIZE": 256,
            "GRID_SIZE": 128,
            "OPTIMIZATION_LEVEL_HOST": 1,
            "MAX_REGISTERS": 100,
            "PRECISION": 64,
            "UNROLL_LOOP_1": 1,
            "UNROLL_LOOP_2": 1,
            "GPUS": 1
        },
        "time": 0.7132911682128906
    },
    {
        "parameters": {
            "OPTIMIZATION_LEVEL_DEVICE": 3,
            "USE_FAST_MATH": 0,
            "BLOCK_SIZE": 256,
            "GRID_SIZE": 256,
            "OPTIMIZATION_LEVEL_HOST": 1,
            "MAX_REGISTERS": 60,
            "PRECISION": 64,
            "UNROLL_LOOP_1": 1,
            "UNROLL_LOOP_2": 1,
            "GPUS": 1
        },
        "time": 0.691749095916748
    },
    {
        "parameters": {
            "OPTIMIZATION_LEVEL_DEVICE": 3,
            "USE_FAST_MATH": 0,
            "BLOCK_SIZE": 256,
            "GRID_SIZE": 4,
            "OPTIMIZATION_LEVEL_HOST": 1,
            "MAX_REGISTERS": -1,
            "PRECISION": 64,
            "UNROLL_LOOP_1": 1,
            "UNROLL_LOOP_2": 1,
            "GPUS": 1
        },
        "time": 0.8259153366088867
    },
    {
        "parameters": {
            "OPTIMIZATION_LEVEL_DEVICE": 3,
            "USE_FAST_MATH": 0,
            "BLOCK_SIZE": 256,
            "GRID_SIZE": 256,
            "OPTIMIZATION_LEVEL_HOST": 1,
            "MAX_REGISTERS": 60,
            "PRECISION": 32,
            "UNROLL_LOOP_1": 1,
            "UNROLL_LOOP_2": 1,
            "GPUS": 1
        },
        "time": 0.7363893985748291
    },
    {
        "parameters": {
            "OPTIMIZATION_LEVEL_DEVICE": 3,
            "USE_FAST_MATH": 0,
            "BLOCK_SIZE": 256,
            "GRID_SIZE": 32,
            "OPTIMIZATION_LEVEL_HOST": 0,
            "MAX_REGISTERS": 60,
            "PRECISION": 64,
            "UNROLL_LOOP_1": 1,
            "UNROLL_LOOP_2": 1,
            "GPUS": 1
        },
        "time": 0.7030091285705566
    },
    {
        "parameters": {
            "OPTIMIZATION_LEVEL_DEVICE": 3,
            "USE_FAST_MATH": 0,
            "BLOCK_SIZE": 256,
            "GRID_SIZE": 128,
            "OPTIMIZATION_LEVEL_HOST": 1,
            "MAX_REGISTERS": -1,
            "PRECISION": 64,
            "UNROLL_LOOP_1": 1,
            "UNROLL_LOOP_2": 1,
            "GPUS": 1
        },
        "time": 0.7056586742401123
    },
    {
        "parameters": {
            "OPTIMIZATION_LEVEL_DEVICE": 3,
            "USE_FAST_MATH": 0,
            "BLOCK_SIZE": 256,
            "GRID_SIZE": 1,
            "OPTIMIZATION_LEVEL_HOST": 2,
            "MAX_REGISTERS": 60,
            "PRECISION": 64,
            "UNROLL_LOOP_1": 1,
            "UNROLL_LOOP_2": 1,
            "GPUS": 1
        },
        "time": 1.2184889316558838
    },
    {
        "parameters": {
            "OPTIMIZATION_LEVEL_DEVICE": 3,
            "USE_FAST_MATH": 0,
            "BLOCK_SIZE": 256,
            "GRID_SIZE": 4,
            "OPTIMIZATION_LEVEL_HOST": 1,
            "MAX_REGISTERS": 20,
            "PRECISION": 64,
            "UNROLL_LOOP_1": 1,
            "UNROLL_LOOP_2": 1,
            "GPUS": 1
        },
        "time": 0.8642184734344482
    },
    {
        "parameters": {
            "OPTIMIZATION_LEVEL_DEVICE": 3,
            "USE_FAST_MATH": 0,
            "BLOCK_SIZE": 256,
            "GRID_SIZE": 8,
            "OPTIMIZATION_LEVEL_HOST": 1,
            "MAX_REGISTERS": 60,
            "PRECISION": 64,
            "UNROLL_LOOP_1": 1,
            "UNROLL_LOOP_2": 1,
            "GPUS": 1
        },
        "time": 0.7755765914916992
    },
    {
        "parameters": {
            "OPTIMIZATION_LEVEL_DEVICE": 3,
            "USE_FAST_MATH": 0,
            "BLOCK_SIZE": 256,
            "GRID_SIZE": 256,
            "OPTIMIZATION_LEVEL_HOST": 1,
            "MAX_REGISTERS": 100,
            "PRECISION": 64,
            "UNROLL_LOOP_1": 1,
            "UNROLL_LOOP_2": 1,
            "GPUS": 1
        },
        "time": 0.7318394184112549
    },
    {
        "parameters": {
            "OPTIMIZATION_LEVEL_DEVICE": 3,
            "USE_FAST_MATH": 0,
            "BLOCK_SIZE": 256,
            "GRID_SIZE": 2,
            "OPTIMIZATION_LEVEL_HOST": 1,
            "MAX_REGISTERS": 60,
            "PRECISION": 64,
            "UNROLL_LOOP_1": 1,
            "UNROLL_LOOP_2": 1,
            "GPUS": 1
        },
        "time": 0.9490697383880615
    },
    {
        "parameters": {
            "OPTIMIZATION_LEVEL_DEVICE": 3,
            "USE_FAST_MATH": 0,
            "BLOCK_SIZE": 256,
            "GRID_SIZE": 256,
            "OPTIMIZATION_LEVEL_HOST": 1,
            "MAX_REGISTERS": 60,
            "PRECISION": 64,
            "UNROLL_LOOP_1": 0,
            "UNROLL_LOOP_2": 1,
            "GPUS": 1
        },
        "time": 0.7374117374420166
    },
    {
        "parameters": {
            "OPTIMIZATION_LEVEL_DEVICE": 3,
            "USE_FAST_MATH": 0,
            "BLOCK_SIZE": 256,
            "GRID_SIZE": 256,
            "OPTIMIZATION_LEVEL_HOST": 0,
            "MAX_REGISTERS": 60,
            "PRECISION": 64,
            "UNROLL_LOOP_1": 1,
            "UNROLL_LOOP_2": 1,
            "GPUS": 1
        },
        "time": 0.7080783843994141
    },
    {
        "parameters": {
            "OPTIMIZATION_LEVEL_DEVICE": 3,
            "USE_FAST_MATH": 1,
            "BLOCK_SIZE": 256,
            "GRID_SIZE": 256,
            "OPTIMIZATION_LEVEL_HOST": 1,
            "MAX_REGISTERS": 60,
            "PRECISION": 32,
            "UNROLL_LOOP_1": 1,
            "UNROLL_LOOP_2": 1,
            "GPUS": 1
        },
        "time": 0.7220516204833984
    },
    {
        "parameters": {
            "OPTIMIZATION_LEVEL_DEVICE": 2,
            "USE_FAST_MATH": 0,
            "BLOCK_SIZE": 256,
            "GRID_SIZE": 4,
            "OPTIMIZATION_LEVEL_HOST": 3,
            "MAX_REGISTERS": 100,
            "PRECISION": 32,
            "UNROLL_LOOP_1": 1,
            "UNROLL_LOOP_2": 0,
            "GPUS": 1
        },
        "time": 0.9403812885284424
    },
    {
        "parameters": {
            "USE_FAST_MATH": 0,
            "GRID_SIZE": 128,
            "BLOCK_SIZE": 128,
            "MAX_REGISTERS": 100,
            "UNROLL_LOOP_2": 1,
            "UNROLL_LOOP_1": 1,
            "PRECISION": 64,
            "OPTIMIZATION_LEVEL_DEVICE": 1,
            "OPTIMIZATION_LEVEL_HOST": 2,
            "GPUS": 1
        },
        "time": 0.7012276649475098
    },
    {
        "parameters": {
            "USE_FAST_MATH": 0,
            "GRID_SIZE": 1,
            "BLOCK_SIZE": 128,
            "MAX_REGISTERS": 120,
            "UNROLL_LOOP_2": 1,
            "UNROLL_LOOP_1": 0,
            "PRECISION": 32,
            "OPTIMIZATION_LEVEL_DEVICE": 0,
            "OPTIMIZATION_LEVEL_HOST": 2,
            "GPUS": 1
        },
        "time": 5.481688976287842
    },
    {
        "parameters": {
            "USE_FAST_MATH": 1,
            "GRID_SIZE": 16,
            "BLOCK_SIZE": 256,
            "MAX_REGISTERS": 120,
            "UNROLL_LOOP_2": 1,
            "UNROLL_LOOP_1": 0,
            "PRECISION": 64,
            "OPTIMIZATION_LEVEL_DEVICE": 3,
            "OPTIMIZATION_LEVEL_HOST": 0,
            "GPUS": 1
        },
        "time": 0.7312595844268799
    },
    {
        "parameters": {
            "OPTIMIZATION_LEVEL_DEVICE": 3,
            "USE_FAST_MATH": 0,
            "BLOCK_SIZE": 256,
            "GRID_SIZE": 256,
            "OPTIMIZATION_LEVEL_HOST": 1,
            "MAX_REGISTERS": -1,
            "PRECISION": 64,
            "UNROLL_LOOP_1": 1,
            "UNROLL_LOOP_2": 1,
            "GPUS": 1
        },
        "time": 0.7713723182678223
    },
    {
        "parameters": {
            "OPTIMIZATION_LEVEL_DEVICE": 3,
            "USE_FAST_MATH": 0,
            "BLOCK_SIZE": 64,
            "GRID_SIZE": 2,
            "OPTIMIZATION_LEVEL_HOST": 1,
            "MAX_REGISTERS": 80,
            "PRECISION": 32,
            "UNROLL_LOOP_1": 1,
            "UNROLL_LOOP_2": 1,
            "GPUS": 1
        },
        "time": 1.5401852130889893
    },
    {
        "parameters": {
            "OPTIMIZATION_LEVEL_DEVICE": 3,
            "USE_FAST_MATH": 0,
            "BLOCK_SIZE": 256,
            "GRID_SIZE": 256,
            "OPTIMIZATION_LEVEL_HOST": 1,
            "MAX_REGISTERS": 20,
            "PRECISION": 64,
            "UNROLL_LOOP_1": 1,
            "UNROLL_LOOP_2": 1,
            "GPUS": 1
        },
        "time": 0.7111907005310059
    },
    {
        "parameters": {
            "OPTIMIZATION_LEVEL_DEVICE": 0,
            "USE_FAST_MATH": 0,
            "BLOCK_SIZE": 256,
            "GRID_SIZE": 128,
            "OPTIMIZATION_LEVEL_HOST": 3,
            "MAX_REGISTERS": 100,
            "PRECISION": 32,
            "UNROLL_LOOP_1": 1,
            "UNROLL_LOOP_2": 0,
            "GPUS": 1
        },
        "time": 0.726616382598877
    },
    {
        "parameters": {
            "OPTIMIZATION_LEVEL_DEVICE": 2,
            "USE_FAST_MATH": 0,
            "BLOCK_SIZE": 512,
            "GRID_SIZE": 256,
            "OPTIMIZATION_LEVEL_HOST": 1,
            "MAX_REGISTERS": 60,
            "PRECISION": 64,
            "UNROLL_LOOP_1": 1,
            "UNROLL_LOOP_2": 1,
            "GPUS": 1
        },
        "time": 0.7255332469940186
    },
    {
        "parameters": {
            "OPTIMIZATION_LEVEL_DEVICE": 3,
            "USE_FAST_MATH": 0,
            "BLOCK_SIZE": 64,
            "GRID_SIZE": 8,
            "OPTIMIZATION_LEVEL_HOST": 1,
            "MAX_REGISTERS": 60,
            "PRECISION": 64,
            "UNROLL_LOOP_1": 1,
            "UNROLL_LOOP_2": 1,
            "GPUS": 1
        },
        "time": 0.8672938346862793
    },
    {
        "parameters": {
            "OPTIMIZATION_LEVEL_DEVICE": 3,
            "USE_FAST_MATH": 0,
            "BLOCK_SIZE": 256,
            "GRID_SIZE": 16,
            "OPTIMIZATION_LEVEL_HOST": 1,
            "MAX_REGISTERS": 60,
            "PRECISION": 64,
            "UNROLL_LOOP_1": 1,
            "UNROLL_LOOP_2": 1,
            "GPUS": 1
        },
        "time": 0.7411930561065674
    },
    {
        "parameters": {
            "OPTIMIZATION_LEVEL_DEVICE": 2,
            "USE_FAST_MATH": 0,
            "BLOCK_SIZE": 256,
            "GRID_SIZE": 256,
            "OPTIMIZATION_LEVEL_HOST": 1,
            "MAX_REGISTERS": 60,
            "PRECISION": 64,
            "UNROLL_LOOP_1": 1,
            "UNROLL_LOOP_2": 1,
            "GPUS": 1
        },
        "time": 0.7324109077453613
    },
    {
        "parameters": {
            "OPTIMIZATION_LEVEL_DEVICE": 0,
            "USE_FAST_MATH": 0,
            "BLOCK_SIZE": 128,
            "GRID_SIZE": 1,
            "OPTIMIZATION_LEVEL_HOST": 3,
            "MAX_REGISTERS": 120,
            "PRECISION": 32,
            "UNROLL_LOOP_1": 0,
            "UNROLL_LOOP_2": 0,
            "GPUS": 1
        },
        "time": 6.430259704589844
    },
    {
        "parameters": {
            "USE_FAST_MATH": 0,
            "GRID_SIZE": 64,
            "BLOCK_SIZE": 128,
            "MAX_REGISTERS": 40,
            "UNROLL_LOOP_2": 0,
            "UNROLL_LOOP_1": 0,
            "PRECISION": 64,
            "OPTIMIZATION_LEVEL_DEVICE": 1,
            "OPTIMIZATION_LEVEL_HOST": 2,
            "GPUS": 1
        },
        "time": 0.7269890308380127
    },
    {
        "parameters": {
            "USE_FAST_MATH": 1,
            "GRID_SIZE": 16,
            "BLOCK_SIZE": 256,
            "MAX_REGISTERS": 100,
            "UNROLL_LOOP_2": 1,
            "UNROLL_LOOP_1": 0,
            "PRECISION": 32,
            "OPTIMIZATION_LEVEL_DEVICE": 3,
            "OPTIMIZATION_LEVEL_HOST": 2,
            "GPUS": 1
        },
        "time": 0.7428371906280518
    },
    {
        "parameters": {
            "USE_FAST_MATH": 0,
            "GRID_SIZE": 1,
            "BLOCK_SIZE": 64,
            "MAX_REGISTERS": 20,
            "UNROLL_LOOP_2": 0,
            "UNROLL_LOOP_1": 0,
            "PRECISION": 64,
            "OPTIMIZATION_LEVEL_DEVICE": 3,
            "OPTIMIZATION_LEVEL_HOST": 2,
            "GPUS": 1
        },
        "time": 2.1639914512634277
    },
    {
        "parameters": {
            "OPTIMIZATION_LEVEL_DEVICE": 3,
            "USE_FAST_MATH": 0,
            "BLOCK_SIZE": 16,
            "GRID_SIZE": 2,
            "OPTIMIZATION_LEVEL_HOST": 1,
            "MAX_REGISTERS": 60,
            "PRECISION": 64,
            "UNROLL_LOOP_1": 1,
            "UNROLL_LOOP_2": 1,
            "GPUS": 1
        },
        "time": 1.905256986618042
    },
    {
        "parameters": {
            "OPTIMIZATION_LEVEL_DEVICE": 3,
            "USE_FAST_MATH": 0,
            "BLOCK_SIZE": 256,
            "GRID_SIZE": 64,
            "OPTIMIZATION_LEVEL_HOST": 1,
            "MAX_REGISTERS": 120,
            "PRECISION": 64,
            "UNROLL_LOOP_1": 1,
            "UNROLL_LOOP_2": 1,
            "GPUS": 1
        },
        "time": 0.6957004070281982
    },
    {
        "parameters": {
            "OPTIMIZATION_LEVEL_DEVICE": 3,
            "USE_FAST_MATH": 0,
            "BLOCK_SIZE": 256,
            "GRID_SIZE": 256,
            "OPTIMIZATION_LEVEL_HOST": 1,
            "MAX_REGISTERS": 80,
            "PRECISION": 64,
            "UNROLL_LOOP_1": 1,
            "UNROLL_LOOP_2": 1,
            "GPUS": 1
        },
        "time": 0.711543083190918
    },
    {
        "parameters": {
            "OPTIMIZATION_LEVEL_DEVICE": 3,
            "USE_FAST_MATH": 0,
            "BLOCK_SIZE": 256,
            "GRID_SIZE": 64,
            "OPTIMIZATION_LEVEL_HOST": 1,
            "MAX_REGISTERS": 60,
            "PRECISION": 64,
            "UNROLL_LOOP_1": 1,
            "UNROLL_LOOP_2": 1,
            "GPUS": 1
        },
        "time": 0.7250621318817139
    },
    {
        "parameters": {
            "OPTIMIZATION_LEVEL_DEVICE": 3,
            "USE_FAST_MATH": 0,
            "BLOCK_SIZE": 16,
            "GRID_SIZE": 8,
            "OPTIMIZATION_LEVEL_HOST": 0,
            "MAX_REGISTERS": 20,
            "PRECISION": 32,
            "UNROLL_LOOP_1": 1,
            "UNROLL_LOOP_2": 0,
            "GPUS": 1
        },
        "time": 1.3706762790679932
    },
    {
        "parameters": {
            "OPTIMIZATION_LEVEL_DEVICE": 2,
            "USE_FAST_MATH": 0,
            "BLOCK_SIZE": 512,
            "GRID_SIZE": 32,
            "OPTIMIZATION_LEVEL_HOST": 0,
            "MAX_REGISTERS": 60,
            "PRECISION": 32,
            "UNROLL_LOOP_1": 0,
            "UNROLL_LOOP_2": 0,
            "GPUS": 1
        },
        "time": 0.7517738342285156
    },
    {
        "parameters": {
            "OPTIMIZATION_LEVEL_DEVICE": 0,
            "USE_FAST_MATH": 0,
            "BLOCK_SIZE": 256,
            "GRID_SIZE": 256,
            "OPTIMIZATION_LEVEL_HOST": 1,
            "MAX_REGISTERS": 40,
            "PRECISION": 64,
            "UNROLL_LOOP_1": 1,
            "UNROLL_LOOP_2": 1,
            "GPUS": 1
        },
        "time": 0.7473831176757812
    },
    {
        "parameters": {
            "OPTIMIZATION_LEVEL_DEVICE": 3,
            "USE_FAST_MATH": 0,
            "BLOCK_SIZE": 256,
            "GRID_SIZE": 256,
            "OPTIMIZATION_LEVEL_HOST": 1,
            "MAX_REGISTERS": 60,
            "PRECISION": 64,
            "UNROLL_LOOP_1": 1,
            "UNROLL_LOOP_2": 0,
            "GPUS": 1
        },
        "time": 0.7071382999420166
    },
    {
        "parameters": {
            "OPTIMIZATION_LEVEL_DEVICE": 3,
            "USE_FAST_MATH": 1,
            "BLOCK_SIZE": 256,
            "GRID_SIZE": 1,
            "OPTIMIZATION_LEVEL_HOST": 1,
            "MAX_REGISTERS": 60,
            "PRECISION": 64,
            "UNROLL_LOOP_1": 1,
            "UNROLL_LOOP_2": 1,
            "GPUS": 1
        },
        "time": 1.2392499446868896
    },
    {
        "parameters": {
            "OPTIMIZATION_LEVEL_DEVICE": 2,
            "USE_FAST_MATH": 0,
            "BLOCK_SIZE": 256,
            "GRID_SIZE": 256,
            "OPTIMIZATION_LEVEL_HOST": 1,
            "MAX_REGISTERS": 120,
            "PRECISION": 64,
            "UNROLL_LOOP_1": 1,
            "UNROLL_LOOP_2": 1,
            "GPUS": 1
        },
        "time": 0.694812536239624
    },
    {
        "parameters": {
            "OPTIMIZATION_LEVEL_DEVICE": 3,
            "USE_FAST_MATH": 0,
            "BLOCK_SIZE": 512,
            "GRID_SIZE": 128,
            "OPTIMIZATION_LEVEL_HOST": 1,
            "MAX_REGISTERS": 20,
            "PRECISION": 64,
            "UNROLL_LOOP_1": 1,
            "UNROLL_LOOP_2": 1,
            "GPUS": 1
        },
        "time": 0.7131836414337158
    },
    {
        "parameters": {
            "OPTIMIZATION_LEVEL_DEVICE": 3,
            "USE_FAST_MATH": 0,
            "BLOCK_SIZE": 256,
            "GRID_SIZE": 256,
            "OPTIMIZATION_LEVEL_HOST": 1,
            "MAX_REGISTERS": 40,
            "PRECISION": 32,
            "UNROLL_LOOP_1": 1,
            "UNROLL_LOOP_2": 1,
            "GPUS": 1
        },
        "time": 0.732306718826294
    },
    {
        "parameters": {
            "USE_FAST_MATH": 1,
            "GRID_SIZE": 64,
            "BLOCK_SIZE": 64,
            "MAX_REGISTERS": 100,
            "UNROLL_LOOP_2": 0,
            "UNROLL_LOOP_1": 1,
            "PRECISION": 32,
            "OPTIMIZATION_LEVEL_DEVICE": 1,
            "OPTIMIZATION_LEVEL_HOST": 3,
            "GPUS": 1
        },
        "time": 0.7373523712158203
    },
    {
        "parameters": {
            "USE_FAST_MATH": 1,
            "GRID_SIZE": 4,
            "BLOCK_SIZE": 64,
            "MAX_REGISTERS": 60,
            "UNROLL_LOOP_2": 0,
            "UNROLL_LOOP_1": 0,
            "PRECISION": 64,
            "OPTIMIZATION_LEVEL_DEVICE": 3,
            "OPTIMIZATION_LEVEL_HOST": 0,
            "GPUS": 1
        },
        "time": 1.085113286972046
    },
    {
        "parameters": {
            "OPTIMIZATION_LEVEL_DEVICE": 3,
            "USE_FAST_MATH": 0,
            "BLOCK_SIZE": 512,
            "GRID_SIZE": 256,
            "OPTIMIZATION_LEVEL_HOST": 1,
            "MAX_REGISTERS": 60,
            "PRECISION": 64,
            "UNROLL_LOOP_1": 1,
            "UNROLL_LOOP_2": 1,
            "GPUS": 1
        },
        "time": 0.718951940536499
    },
    {
        "parameters": {
            "OPTIMIZATION_LEVEL_DEVICE": 3,
            "USE_FAST_MATH": 0,
            "BLOCK_SIZE": 256,
            "GRID_SIZE": 64,
            "OPTIMIZATION_LEVEL_HOST": 1,
            "MAX_REGISTERS": -1,
            "PRECISION": 64,
            "UNROLL_LOOP_1": 1,
            "UNROLL_LOOP_2": 1,
            "GPUS": 1
        },
        "time": 0.7105190753936768
    },
    {
        "parameters": {
            "OPTIMIZATION_LEVEL_DEVICE": 3,
            "USE_FAST_MATH": 0,
            "BLOCK_SIZE": 256,
            "GRID_SIZE": 256,
            "OPTIMIZATION_LEVEL_HOST": 1,
            "MAX_REGISTERS": 120,
            "PRECISION": 32,
            "UNROLL_LOOP_1": 1,
            "UNROLL_LOOP_2": 1,
            "GPUS": 1
        },
        "time": 0.7155873775482178
    },
    {
        "parameters": {
            "OPTIMIZATION_LEVEL_DEVICE": 3,
            "USE_FAST_MATH": 0,
            "BLOCK_SIZE": 64,
            "GRID_SIZE": 32,
            "OPTIMIZATION_LEVEL_HOST": 2,
            "MAX_REGISTERS": 40,
            "PRECISION": 32,
            "UNROLL_LOOP_1": 1,
            "UNROLL_LOOP_2": 0,
            "GPUS": 1
        },
        "time": 0.7798564434051514
    },
    {
        "parameters": {
            "OPTIMIZATION_LEVEL_DEVICE": 2,
            "USE_FAST_MATH": 0,
            "BLOCK_SIZE": 64,
            "GRID_SIZE": 4,
            "OPTIMIZATION_LEVEL_HOST": 2,
            "MAX_REGISTERS": 60,
            "PRECISION": 64,
            "UNROLL_LOOP_1": 0,
            "UNROLL_LOOP_2": 1,
            "GPUS": 1
        },
        "time": 0.960599422454834
    },
    {
        "parameters": {
            "OPTIMIZATION_LEVEL_DEVICE": 3,
            "USE_FAST_MATH": 0,
            "BLOCK_SIZE": 512,
            "GRID_SIZE": 128,
            "OPTIMIZATION_LEVEL_HOST": 1,
            "MAX_REGISTERS": 60,
            "PRECISION": 64,
            "UNROLL_LOOP_1": 1,
            "UNROLL_LOOP_2": 1,
            "GPUS": 1
        },
        "time": 0.7272171974182129
    },
    {
        "parameters": {
            "OPTIMIZATION_LEVEL_DEVICE": 2,
            "USE_FAST_MATH": 0,
            "BLOCK_SIZE": 256,
            "GRID_SIZE": 256,
            "OPTIMIZATION_LEVEL_HOST": 0,
            "MAX_REGISTERS": 60,
            "PRECISION": 64,
            "UNROLL_LOOP_1": 1,
            "UNROLL_LOOP_2": 1,
            "GPUS": 1
        },
        "time": 0.6934034824371338
    },
    {
        "parameters": {
            "USE_FAST_MATH": 1,
            "GRID_SIZE": 64,
            "BLOCK_SIZE": 128,
            "MAX_REGISTERS": 120,
            "UNROLL_LOOP_2": 0,
            "UNROLL_LOOP_1": 0,
            "PRECISION": 64,
            "OPTIMIZATION_LEVEL_DEVICE": 3,
            "OPTIMIZATION_LEVEL_HOST": 0,
            "GPUS": 1
        },
        "time": 0.7222254276275635
    },
    {
        "parameters": {
            "OPTIMIZATION_LEVEL_DEVICE": 3,
            "USE_FAST_MATH": 0,
            "BLOCK_SIZE": 256,
            "GRID_SIZE": 64,
            "OPTIMIZATION_LEVEL_HOST": 1,
            "MAX_REGISTERS": 60,
            "PRECISION": 32,
            "UNROLL_LOOP_1": 1,
            "UNROLL_LOOP_2": 1,
            "GPUS": 1
        },
        "time": 0.7228362560272217
    },
    {
        "parameters": {
            "OPTIMIZATION_LEVEL_DEVICE": 3,
            "USE_FAST_MATH": 0,
            "BLOCK_SIZE": 128,
            "GRID_SIZE": 4,
            "OPTIMIZATION_LEVEL_HOST": 1,
            "MAX_REGISTERS": 60,
            "PRECISION": 64,
            "UNROLL_LOOP_1": 1,
            "UNROLL_LOOP_2": 1,
            "GPUS": 1
        },
        "time": 0.8728747367858887
    },
    {
        "parameters": {
            "OPTIMIZATION_LEVEL_DEVICE": 3,
            "USE_FAST_MATH": 0,
            "BLOCK_SIZE": 256,
            "GRID_SIZE": 4,
            "OPTIMIZATION_LEVEL_HOST": 1,
            "MAX_REGISTERS": 60,
            "PRECISION": 64,
            "UNROLL_LOOP_1": 1,
            "UNROLL_LOOP_2": 1,
            "GPUS": 1
        },
        "time": 0.8689661026000977
    },
    {
        "parameters": {
            "OPTIMIZATION_LEVEL_DEVICE": 3,
            "USE_FAST_MATH": 0,
            "BLOCK_SIZE": 256,
            "GRID_SIZE": 256,
            "OPTIMIZATION_LEVEL_HOST": 2,
            "MAX_REGISTERS": 80,
            "PRECISION": 64,
            "UNROLL_LOOP_1": 1,
            "UNROLL_LOOP_2": 1,
            "GPUS": 1
        },
        "time": 0.7383153438568115
    },
    {
        "parameters": {
            "OPTIMIZATION_LEVEL_DEVICE": 3,
            "USE_FAST_MATH": 0,
            "BLOCK_SIZE": 256,
            "GRID_SIZE": 256,
            "OPTIMIZATION_LEVEL_HOST": 2,
            "MAX_REGISTERS": 60,
            "PRECISION": 64,
            "UNROLL_LOOP_1": 1,
            "UNROLL_LOOP_2": 1,
            "GPUS": 1
        },
        "time": 0.7056355476379395
    },
    {
        "parameters": {
            "OPTIMIZATION_LEVEL_DEVICE": 3,
            "USE_FAST_MATH": 0,
            "BLOCK_SIZE": 256,
            "GRID_SIZE": 256,
            "OPTIMIZATION_LEVEL_HOST": 1,
            "MAX_REGISTERS": 40,
            "PRECISION": 64,
            "UNROLL_LOOP_1": 1,
            "UNROLL_LOOP_2": 1,
            "GPUS": 1
        },
        "time": 0.7107255458831787
    },
    {
        "parameters": {
            "OPTIMIZATION_LEVEL_DEVICE": 3,
            "USE_FAST_MATH": 0,
            "BLOCK_SIZE": 256,
            "GRID_SIZE": 16,
            "OPTIMIZATION_LEVEL_HOST": 1,
            "MAX_REGISTERS": 80,
            "PRECISION": 32,
            "UNROLL_LOOP_1": 1,
            "UNROLL_LOOP_2": 1,
            "GPUS": 1
        },
        "time": 0.7795741558074951
    },
    {
        "parameters": {
            "OPTIMIZATION_LEVEL_DEVICE": 3,
            "USE_FAST_MATH": 0,
            "BLOCK_SIZE": 512,
            "GRID_SIZE": 256,
            "OPTIMIZATION_LEVEL_HOST": 1,
            "MAX_REGISTERS": 20,
            "PRECISION": 32,
            "UNROLL_LOOP_1": 1,
            "UNROLL_LOOP_2": 1,
            "GPUS": 1
        },
        "time": 0.7208960056304932
    },
    {
        "parameters": {
            "OPTIMIZATION_LEVEL_DEVICE": 3,
            "USE_FAST_MATH": 0,
            "BLOCK_SIZE": 256,
            "GRID_SIZE": 4,
            "OPTIMIZATION_LEVEL_HOST": 0,
            "MAX_REGISTERS": 60,
            "PRECISION": 32,
            "UNROLL_LOOP_1": 1,
            "UNROLL_LOOP_2": 1,
            "GPUS": 1
        },
        "time": 0.8941249847412109
    },
    {
        "parameters": {
            "OPTIMIZATION_LEVEL_DEVICE": 2,
            "USE_FAST_MATH": 0,
            "BLOCK_SIZE": 512,
            "GRID_SIZE": 256,
            "OPTIMIZATION_LEVEL_HOST": 1,
            "MAX_REGISTERS": 20,
            "PRECISION": 64,
            "UNROLL_LOOP_1": 1,
            "UNROLL_LOOP_2": 1,
            "GPUS": 1
        },
        "time": 0.7161176204681396
    },
    {
        "parameters": {
            "OPTIMIZATION_LEVEL_DEVICE": 3,
            "USE_FAST_MATH": 0,
            "BLOCK_SIZE": 256,
            "GRID_SIZE": 256,
            "OPTIMIZATION_LEVEL_HOST": 1,
            "MAX_REGISTERS": 80,
            "PRECISION": 32,
            "UNROLL_LOOP_1": 1,
            "UNROLL_LOOP_2": 1,
            "GPUS": 1
        },
        "time": 0.7110326290130615
    },
    {
        "parameters": {
            "OPTIMIZATION_LEVEL_DEVICE": 3,
            "USE_FAST_MATH": 0,
            "BLOCK_SIZE": 256,
            "GRID_SIZE": 32,
            "OPTIMIZATION_LEVEL_HOST": 1,
            "MAX_REGISTERS": 120,
            "PRECISION": 32,
            "UNROLL_LOOP_1": 1,
            "UNROLL_LOOP_2": 1,
            "GPUS": 1
        },
        "time": 0.7397723197937012
    },
    {
        "parameters": {
            "OPTIMIZATION_LEVEL_DEVICE": 3,
            "USE_FAST_MATH": 0,
            "BLOCK_SIZE": 512,
            "GRID_SIZE": 256,
            "OPTIMIZATION_LEVEL_HOST": 1,
            "MAX_REGISTERS": 60,
            "PRECISION": 32,
            "UNROLL_LOOP_1": 1,
            "UNROLL_LOOP_2": 1,
            "GPUS": 1
        },
        "time": 0.7265927791595459
    },
    {
        "parameters": {
            "OPTIMIZATION_LEVEL_DEVICE": 3,
            "USE_FAST_MATH": 0,
            "BLOCK_SIZE": 256,
            "GRID_SIZE": 256,
            "OPTIMIZATION_LEVEL_HOST": 0,
            "MAX_REGISTERS": 60,
            "PRECISION": 32,
            "UNROLL_LOOP_1": 1,
            "UNROLL_LOOP_2": 1,
            "GPUS": 1
        },
        "time": 0.6983733177185059
    },
    {
        "parameters": {
            "OPTIMIZATION_LEVEL_DEVICE": 3,
            "USE_FAST_MATH": 0,
            "BLOCK_SIZE": 256,
            "GRID_SIZE": 4,
            "OPTIMIZATION_LEVEL_HOST": 1,
            "MAX_REGISTERS": 60,
            "PRECISION": 32,
            "UNROLL_LOOP_1": 1,
            "UNROLL_LOOP_2": 1,
            "GPUS": 1
        },
        "time": 0.8649094104766846
    },
    {
        "parameters": {
            "OPTIMIZATION_LEVEL_DEVICE": 3,
            "USE_FAST_MATH": 0,
            "BLOCK_SIZE": 16,
            "GRID_SIZE": 16,
            "OPTIMIZATION_LEVEL_HOST": 1,
            "MAX_REGISTERS": 60,
            "PRECISION": 64,
            "UNROLL_LOOP_1": 1,
            "UNROLL_LOOP_2": 1,
            "GPUS": 1
        },
        "time": 0.8948628902435303
    },
    {
        "parameters": {
            "OPTIMIZATION_LEVEL_DEVICE": 2,
            "USE_FAST_MATH": 0,
            "BLOCK_SIZE": 256,
            "GRID_SIZE": 128,
            "OPTIMIZATION_LEVEL_HOST": 1,
            "MAX_REGISTERS": 60,
            "PRECISION": 64,
            "UNROLL_LOOP_1": 1,
            "UNROLL_LOOP_2": 1,
            "GPUS": 1
        },
        "time": 0.705214262008667
    },
    {
        "parameters": {
            "OPTIMIZATION_LEVEL_DEVICE": 3,
            "USE_FAST_MATH": 0,
            "BLOCK_SIZE": 256,
            "GRID_SIZE": 16,
            "OPTIMIZATION_LEVEL_HOST": 1,
            "MAX_REGISTERS": 40,
            "PRECISION": 64,
            "UNROLL_LOOP_1": 1,
            "UNROLL_LOOP_2": 1,
            "GPUS": 1
        },
        "time": 0.7417359352111816
    },
    {
        "parameters": {
            "OPTIMIZATION_LEVEL_DEVICE": 3,
            "USE_FAST_MATH": 0,
            "BLOCK_SIZE": 256,
            "GRID_SIZE": 256,
            "OPTIMIZATION_LEVEL_HOST": 0,
            "MAX_REGISTERS": 80,
            "PRECISION": 64,
            "UNROLL_LOOP_1": 1,
            "UNROLL_LOOP_2": 1,
            "GPUS": 1
        },
        "time": 0.7320821285247803
    },
    {
        "parameters": {
            "OPTIMIZATION_LEVEL_DEVICE": 3,
            "USE_FAST_MATH": 0,
            "BLOCK_SIZE": 256,
            "GRID_SIZE": 2,
            "OPTIMIZATION_LEVEL_HOST": 1,
            "MAX_REGISTERS": 100,
            "PRECISION": 64,
            "UNROLL_LOOP_1": 1,
            "UNROLL_LOOP_2": 1,
            "GPUS": 1
        },
        "time": 0.9436478614807129
    },
    {
        "parameters": {
            "OPTIMIZATION_LEVEL_DEVICE": 2,
            "USE_FAST_MATH": 0,
            "BLOCK_SIZE": 128,
            "GRID_SIZE": 128,
            "OPTIMIZATION_LEVEL_HOST": 3,
            "MAX_REGISTERS": -1,
            "PRECISION": 32,
            "UNROLL_LOOP_1": 1,
            "UNROLL_LOOP_2": 0,
            "GPUS": 1
        },
        "time": 0.722414493560791
    },
    {
        "parameters": {
            "USE_FAST_MATH": 1,
            "GRID_SIZE": 16,
            "BLOCK_SIZE": 128,
            "MAX_REGISTERS": 60,
            "UNROLL_LOOP_2": 1,
            "UNROLL_LOOP_1": 0,
            "PRECISION": 64,
            "OPTIMIZATION_LEVEL_DEVICE": 0,
            "OPTIMIZATION_LEVEL_HOST": 3,
            "GPUS": 1
        },
        "time": 0.9018011093139648
    },
    {
        "parameters": {
            "USE_FAST_MATH": 1,
            "GRID_SIZE": 32,
            "BLOCK_SIZE": 256,
            "MAX_REGISTERS": 20,
            "UNROLL_LOOP_2": 1,
            "UNROLL_LOOP_1": 1,
            "PRECISION": 32,
            "OPTIMIZATION_LEVEL_DEVICE": 3,
            "OPTIMIZATION_LEVEL_HOST": 0,
            "GPUS": 1
        },
        "time": 0.7486531734466553
    },
    {
        "parameters": {
            "USE_FAST_MATH": 1,
            "GRID_SIZE": 2,
            "BLOCK_SIZE": 16,
            "MAX_REGISTERS": 120,
            "UNROLL_LOOP_2": 0,
            "UNROLL_LOOP_1": 1,
            "PRECISION": 32,
            "OPTIMIZATION_LEVEL_DEVICE": 1,
            "OPTIMIZATION_LEVEL_HOST": 2,
            "GPUS": 1
        },
        "time": 3.479808807373047
    },
    {
        "parameters": {
            "OPTIMIZATION_LEVEL_DEVICE": 0,
            "USE_FAST_MATH": 0,
            "BLOCK_SIZE": 256,
            "GRID_SIZE": 256,
            "OPTIMIZATION_LEVEL_HOST": 1,
            "MAX_REGISTERS": 60,
            "PRECISION": 64,
            "UNROLL_LOOP_1": 0,
            "UNROLL_LOOP_2": 1,
            "GPUS": 1
        },
        "time": 0.7526791095733643
    },
    {
        "parameters": {
            "OPTIMIZATION_LEVEL_DEVICE": 1,
            "USE_FAST_MATH": 0,
            "BLOCK_SIZE": 256,
            "GRID_SIZE": 256,
            "OPTIMIZATION_LEVEL_HOST": 1,
            "MAX_REGISTERS": 60,
            "PRECISION": 64,
            "UNROLL_LOOP_1": 1,
            "UNROLL_LOOP_2": 0,
            "GPUS": 1
        },
        "time": 0.7207129001617432
    },
    {
        "parameters": {
            "OPTIMIZATION_LEVEL_DEVICE": 2,
            "USE_FAST_MATH": 0,
            "BLOCK_SIZE": 256,
            "GRID_SIZE": 128,
            "OPTIMIZATION_LEVEL_HOST": 0,
            "MAX_REGISTERS": 120,
            "PRECISION": 32,
            "UNROLL_LOOP_1": 1,
            "UNROLL_LOOP_2": 0,
            "GPUS": 1
        },
        "time": 0.7215850353240967
    },
    {
        "parameters": {
            "OPTIMIZATION_LEVEL_DEVICE": 3,
            "USE_FAST_MATH": 0,
            "BLOCK_SIZE": 256,
            "GRID_SIZE": 256,
            "OPTIMIZATION_LEVEL_HOST": 1,
            "MAX_REGISTERS": 100,
            "PRECISION": 32,
            "UNROLL_LOOP_1": 1,
            "UNROLL_LOOP_2": 1,
            "GPUS": 1
        },
        "time": 0.7277481555938721
    },
    {
        "parameters": {
            "OPTIMIZATION_LEVEL_DEVICE": 3,
            "USE_FAST_MATH": 0,
            "BLOCK_SIZE": 512,
            "GRID_SIZE": 256,
            "OPTIMIZATION_LEVEL_HOST": 2,
            "MAX_REGISTERS": 60,
            "PRECISION": 64,
            "UNROLL_LOOP_1": 1,
            "UNROLL_LOOP_2": 1,
            "GPUS": 1
        },
        "time": 0.7189438343048096
    },
    {
        "parameters": {
            "OPTIMIZATION_LEVEL_DEVICE": 2,
            "USE_FAST_MATH": 0,
            "BLOCK_SIZE": 256,
            "GRID_SIZE": 256,
            "OPTIMIZATION_LEVEL_HOST": 1,
            "MAX_REGISTERS": 60,
            "PRECISION": 32,
            "UNROLL_LOOP_1": 1,
            "UNROLL_LOOP_2": 1,
            "GPUS": 1
        },
        "time": 0.7088279724121094
    },
    {
        "parameters": {
            "OPTIMIZATION_LEVEL_DEVICE": 3,
            "USE_FAST_MATH": 1,
            "BLOCK_SIZE": 256,
            "GRID_SIZE": 1,
            "OPTIMIZATION_LEVEL_HOST": 1,
            "MAX_REGISTERS": 120,
            "PRECISION": 64,
            "UNROLL_LOOP_1": 1,
            "UNROLL_LOOP_2": 1,
            "GPUS": 1
        },
        "time": 1.2092738151550293
    },
    {
        "parameters": {
            "OPTIMIZATION_LEVEL_DEVICE": 3,
            "USE_FAST_MATH": 1,
            "BLOCK_SIZE": 256,
            "GRID_SIZE": 256,
            "OPTIMIZATION_LEVEL_HOST": 1,
            "MAX_REGISTERS": 60,
            "PRECISION": 64,
            "UNROLL_LOOP_1": 1,
            "UNROLL_LOOP_2": 1,
            "GPUS": 1
        },
        "time": 0.7005822658538818
    },
    {
        "parameters": {
            "OPTIMIZATION_LEVEL_DEVICE": 3,
            "USE_FAST_MATH": 0,
            "BLOCK_SIZE": 128,
            "GRID_SIZE": 1,
            "OPTIMIZATION_LEVEL_HOST": 0,
            "MAX_REGISTERS": 60,
            "PRECISION": 32,
            "UNROLL_LOOP_1": 1,
            "UNROLL_LOOP_2": 0,
            "GPUS": 1
        },
        "time": 2.1105642318725586
    },
    {
        "parameters": {
            "USE_FAST_MATH": 0,
            "GRID_SIZE": 1,
            "BLOCK_SIZE": 64,
            "MAX_REGISTERS": 20,
            "UNROLL_LOOP_2": 0,
            "UNROLL_LOOP_1": 0,
            "PRECISION": 32,
            "OPTIMIZATION_LEVEL_DEVICE": 0,
            "OPTIMIZATION_LEVEL_HOST": 1,
            "GPUS": 1
        },
        "time": 11.566106796264648
    },
    {
        "parameters": {
            "USE_FAST_MATH": 0,
            "GRID_SIZE": 1,
            "BLOCK_SIZE": 16,
            "MAX_REGISTERS": 100,
            "UNROLL_LOOP_2": 0,
            "UNROLL_LOOP_1": 1,
            "PRECISION": 32,
            "OPTIMIZATION_LEVEL_DEVICE": 2,
            "OPTIMIZATION_LEVEL_HOST": 1,
            "GPUS": 1
        },
        "time": 5.016116142272949
    },
    {
        "parameters": {
            "USE_FAST_MATH": 0,
            "GRID_SIZE": 128,
            "BLOCK_SIZE": 512,
            "MAX_REGISTERS": 20,
            "UNROLL_LOOP_2": 1,
            "UNROLL_LOOP_1": 0,
            "PRECISION": 32,
            "OPTIMIZATION_LEVEL_DEVICE": 3,
            "OPTIMIZATION_LEVEL_HOST": 1,
            "GPUS": 1
        },
        "time": 0.7221403121948242
    },
    {
        "parameters": {
            "OPTIMIZATION_LEVEL_DEVICE": 3,
            "USE_FAST_MATH": 0,
            "BLOCK_SIZE": 256,
            "GRID_SIZE": 1,
            "OPTIMIZATION_LEVEL_HOST": 1,
            "MAX_REGISTERS": 40,
            "PRECISION": 64,
            "UNROLL_LOOP_1": 1,
            "UNROLL_LOOP_2": 1,
            "GPUS": 1
        },
        "time": 1.2341465950012207
    },
    {
        "parameters": {
            "OPTIMIZATION_LEVEL_DEVICE": 3,
            "USE_FAST_MATH": 0,
            "BLOCK_SIZE": 128,
            "GRID_SIZE": 128,
            "OPTIMIZATION_LEVEL_HOST": 0,
            "MAX_REGISTERS": 100,
            "PRECISION": 32,
            "UNROLL_LOOP_1": 1,
            "UNROLL_LOOP_2": 0,
            "GPUS": 1
        },
        "time": 0.75417160987854
    },
    {
        "parameters": {
            "USE_FAST_MATH": 0,
            "GRID_SIZE": 128,
            "BLOCK_SIZE": 512,
            "MAX_REGISTERS": 100,
            "UNROLL_LOOP_2": 0,
            "UNROLL_LOOP_1": 1,
            "PRECISION": 32,
            "OPTIMIZATION_LEVEL_DEVICE": 0,
            "OPTIMIZATION_LEVEL_HOST": 0,
            "GPUS": 1
        },
        "time": 0.7640237808227539
    },
    {
        "parameters": {
            "USE_FAST_MATH": 1,
            "GRID_SIZE": 256,
            "BLOCK_SIZE": 512,
            "MAX_REGISTERS": 100,
            "UNROLL_LOOP_2": 1,
            "UNROLL_LOOP_1": 1,
            "PRECISION": 64,
            "OPTIMIZATION_LEVEL_DEVICE": 0,
            "OPTIMIZATION_LEVEL_HOST": 2,
            "GPUS": 1
        },
        "time": 0.7268285751342773
    },
    {
        "parameters": {
            "OPTIMIZATION_LEVEL_DEVICE": 3,
            "USE_FAST_MATH": 0,
            "BLOCK_SIZE": 256,
            "GRID_SIZE": 256,
            "OPTIMIZATION_LEVEL_HOST": 3,
            "MAX_REGISTERS": 60,
            "PRECISION": 32,
            "UNROLL_LOOP_1": 1,
            "UNROLL_LOOP_2": 1,
            "GPUS": 1
        },
        "time": 0.7658782005310059
    },
    {
        "parameters": {
            "OPTIMIZATION_LEVEL_DEVICE": 3,
            "USE_FAST_MATH": 0,
            "BLOCK_SIZE": 256,
            "GRID_SIZE": 256,
            "OPTIMIZATION_LEVEL_HOST": 1,
            "MAX_REGISTERS": 120,
            "PRECISION": 64,
            "UNROLL_LOOP_1": 1,
            "UNROLL_LOOP_2": 1,
            "GPUS": 1
        },
        "time": 0.701817512512207
    },
    {
        "parameters": {
            "OPTIMIZATION_LEVEL_DEVICE": 3,
            "USE_FAST_MATH": 1,
            "BLOCK_SIZE": 256,
            "GRID_SIZE": 256,
            "OPTIMIZATION_LEVEL_HOST": 1,
            "MAX_REGISTERS": 60,
            "PRECISION": 64,
            "UNROLL_LOOP_1": 0,
            "UNROLL_LOOP_2": 1,
            "GPUS": 1
        },
        "time": 0.695267915725708
    },
    {
        "parameters": {
            "OPTIMIZATION_LEVEL_DEVICE": 3,
            "USE_FAST_MATH": 0,
            "BLOCK_SIZE": 256,
            "GRID_SIZE": 32,
            "OPTIMIZATION_LEVEL_HOST": 1,
            "MAX_REGISTERS": 60,
            "PRECISION": 64,
            "UNROLL_LOOP_1": 1,
            "UNROLL_LOOP_2": 1,
            "GPUS": 1
        },
        "time": 0.7323424816131592
    },
    {
        "parameters": {
            "OPTIMIZATION_LEVEL_DEVICE": 3,
            "USE_FAST_MATH": 0,
            "BLOCK_SIZE": 256,
            "GRID_SIZE": 8,
            "OPTIMIZATION_LEVEL_HOST": 1,
            "MAX_REGISTERS": 40,
            "PRECISION": 32,
            "UNROLL_LOOP_1": 1,
            "UNROLL_LOOP_2": 1,
            "GPUS": 1
        },
        "time": 0.8058173656463623
    },
    {
        "parameters": {
            "OPTIMIZATION_LEVEL_DEVICE": 2,
            "USE_FAST_MATH": 0,
            "BLOCK_SIZE": 512,
            "GRID_SIZE": 64,
            "OPTIMIZATION_LEVEL_HOST": 1,
            "MAX_REGISTERS": 100,
            "PRECISION": 64,
            "UNROLL_LOOP_1": 0,
            "UNROLL_LOOP_2": 0,
            "GPUS": 1
        },
        "time": 0.7100613117218018
    },
    {
        "parameters": {
            "OPTIMIZATION_LEVEL_DEVICE": 3,
            "USE_FAST_MATH": 0,
            "BLOCK_SIZE": 64,
            "GRID_SIZE": 4,
            "OPTIMIZATION_LEVEL_HOST": 0,
            "MAX_REGISTERS": 20,
            "PRECISION": 32,
            "UNROLL_LOOP_1": 1,
            "UNROLL_LOOP_2": 0,
            "GPUS": 1
        },
        "time": 1.3360779285430908
    },
    {
        "parameters": {
            "USE_FAST_MATH": 1,
            "GRID_SIZE": 4,
            "BLOCK_SIZE": 512,
            "MAX_REGISTERS": 120,
            "UNROLL_LOOP_2": 1,
            "UNROLL_LOOP_1": 1,
            "PRECISION": 64,
            "OPTIMIZATION_LEVEL_DEVICE": 1,
            "OPTIMIZATION_LEVEL_HOST": 0,
            "GPUS": 1
        },
        "time": 0.8136563301086426
    },
    {
        "parameters": {
            "USE_FAST_MATH": 0,
            "GRID_SIZE": 2,
            "BLOCK_SIZE": 256,
            "MAX_REGISTERS": 100,
            "UNROLL_LOOP_2": 1,
            "UNROLL_LOOP_1": 1,
            "PRECISION": 64,
            "OPTIMIZATION_LEVEL_DEVICE": 0,
            "OPTIMIZATION_LEVEL_HOST": 1,
            "GPUS": 1
        },
        "time": 1.3936991691589355
    },
    {
        "parameters": {
            "USE_FAST_MATH": 0,
            "GRID_SIZE": 64,
            "BLOCK_SIZE": 64,
            "MAX_REGISTERS": 120,
            "UNROLL_LOOP_2": 1,
            "UNROLL_LOOP_1": 1,
            "PRECISION": 32,
            "OPTIMIZATION_LEVEL_DEVICE": 2,
            "OPTIMIZATION_LEVEL_HOST": 1,
            "GPUS": 1
        },
        "time": 0.7209818363189697
    },
    {
        "parameters": {
            "OPTIMIZATION_LEVEL_DEVICE": 0,
            "USE_FAST_MATH": 0,
            "BLOCK_SIZE": 128,
            "GRID_SIZE": 1,
            "OPTIMIZATION_LEVEL_HOST": 1,
            "MAX_REGISTERS": 20,
            "PRECISION": 64,
            "UNROLL_LOOP_1": 1,
            "UNROLL_LOOP_2": 0,
            "GPUS": 1
        },
        "time": 3.587388277053833
    },
    {
        "parameters": {
            "OPTIMIZATION_LEVEL_DEVICE": 3,
            "USE_FAST_MATH": 0,
            "BLOCK_SIZE": 256,
            "GRID_SIZE": 256,
            "OPTIMIZATION_LEVEL_HOST": 3,
            "MAX_REGISTERS": 60,
            "PRECISION": 64,
            "UNROLL_LOOP_1": 1,
            "UNROLL_LOOP_2": 1,
            "GPUS": 1
        },
        "time": 0.7213761806488037
    },
    {
        "parameters": {
            "OPTIMIZATION_LEVEL_DEVICE": 3,
            "USE_FAST_MATH": 1,
            "BLOCK_SIZE": 256,
            "GRID_SIZE": 256,
            "OPTIMIZATION_LEVEL_HOST": 0,
            "MAX_REGISTERS": -1,
            "PRECISION": 64,
            "UNROLL_LOOP_1": 1,
            "UNROLL_LOOP_2": 1,
            "GPUS": 1
        },
        "time": 0.7254924774169922
    },
    {
        "parameters": {
            "OPTIMIZATION_LEVEL_DEVICE": 3,
            "USE_FAST_MATH": 0,
            "BLOCK_SIZE": 512,
            "GRID_SIZE": 8,
            "OPTIMIZATION_LEVEL_HOST": 1,
            "MAX_REGISTERS": 120,
            "PRECISION": 32,
            "UNROLL_LOOP_1": 1,
            "UNROLL_LOOP_2": 1,
            "GPUS": 1
        },
        "time": 0.807166576385498
    },
    {
        "parameters": {
            "OPTIMIZATION_LEVEL_DEVICE": 2,
            "USE_FAST_MATH": 0,
            "BLOCK_SIZE": 256,
            "GRID_SIZE": 256,
            "OPTIMIZATION_LEVEL_HOST": 0,
            "MAX_REGISTERS": 120,
            "PRECISION": 32,
            "UNROLL_LOOP_1": 0,
            "UNROLL_LOOP_2": 0,
            "GPUS": 1
        },
        "time": 0.7242085933685303
    },
    {
        "parameters": {
            "OPTIMIZATION_LEVEL_DEVICE": 3,
            "USE_FAST_MATH": 0,
            "BLOCK_SIZE": 64,
            "GRID_SIZE": 16,
            "OPTIMIZATION_LEVEL_HOST": 0,
            "MAX_REGISTERS": 100,
            "PRECISION": 32,
            "UNROLL_LOOP_1": 0,
            "UNROLL_LOOP_2": 0,
            "GPUS": 1
        },
        "time": 0.8968760967254639
    },
    {
        "parameters": {
            "OPTIMIZATION_LEVEL_DEVICE": 3,
            "USE_FAST_MATH": 0,
            "BLOCK_SIZE": 64,
            "GRID_SIZE": 32,
            "OPTIMIZATION_LEVEL_HOST": 0,
            "MAX_REGISTERS": 40,
            "PRECISION": 64,
            "UNROLL_LOOP_1": 0,
            "UNROLL_LOOP_2": 0,
            "GPUS": 1
        },
        "time": 0.7564771175384521
    },
    {
        "parameters": {
            "OPTIMIZATION_LEVEL_DEVICE": 2,
            "USE_FAST_MATH": 0,
            "BLOCK_SIZE": 512,
            "GRID_SIZE": 8,
            "OPTIMIZATION_LEVEL_HOST": 2,
            "MAX_REGISTERS": 40,
            "PRECISION": 32,
            "UNROLL_LOOP_1": 0,
            "UNROLL_LOOP_2": 0,
            "GPUS": 1
        },
        "time": 0.7789273262023926
    },
    {
        "parameters": {
            "USE_FAST_MATH": 0,
            "GRID_SIZE": 16,
            "BLOCK_SIZE": 512,
            "MAX_REGISTERS": 60,
            "UNROLL_LOOP_2": 0,
            "UNROLL_LOOP_1": 0,
            "PRECISION": 64,
            "OPTIMIZATION_LEVEL_DEVICE": 0,
            "OPTIMIZATION_LEVEL_HOST": 0,
            "GPUS": 1
        },
        "time": 0.7803401947021484
    },
    {
        "parameters": {
            "USE_FAST_MATH": 0,
            "GRID_SIZE": 1,
            "BLOCK_SIZE": 512,
            "MAX_REGISTERS": 40,
            "UNROLL_LOOP_2": 0,
            "UNROLL_LOOP_1": 0,
            "PRECISION": 64,
            "OPTIMIZATION_LEVEL_DEVICE": 1,
            "OPTIMIZATION_LEVEL_HOST": 2,
            "GPUS": 1
        },
        "time": 1.2600281238555908
    },
    {
        "parameters": {
            "USE_FAST_MATH": 0,
            "GRID_SIZE": 16,
            "BLOCK_SIZE": 128,
            "MAX_REGISTERS": -1,
            "UNROLL_LOOP_2": 1,
            "UNROLL_LOOP_1": 1,
            "PRECISION": 32,
            "OPTIMIZATION_LEVEL_DEVICE": 1,
            "OPTIMIZATION_LEVEL_HOST": 2,
            "GPUS": 1
        },
        "time": 0.7757384777069092
    },
    {
        "parameters": {
            "OPTIMIZATION_LEVEL_DEVICE": 1,
            "USE_FAST_MATH": 1,
            "BLOCK_SIZE": 256,
            "GRID_SIZE": 256,
            "OPTIMIZATION_LEVEL_HOST": 0,
            "MAX_REGISTERS": 60,
            "PRECISION": 64,
            "UNROLL_LOOP_1": 1,
            "UNROLL_LOOP_2": 1,
            "GPUS": 1
        },
        "time": 0.7129051685333252
    },
    {
        "parameters": {
            "OPTIMIZATION_LEVEL_DEVICE": 3,
            "USE_FAST_MATH": 0,
            "BLOCK_SIZE": 256,
            "GRID_SIZE": 128,
            "OPTIMIZATION_LEVEL_HOST": 0,
            "MAX_REGISTERS": 60,
            "PRECISION": 64,
            "UNROLL_LOOP_1": 1,
            "UNROLL_LOOP_2": 1,
            "GPUS": 1
        },
        "time": 0.695582389831543
    },
    {
        "parameters": {
            "OPTIMIZATION_LEVEL_DEVICE": 3,
            "USE_FAST_MATH": 0,
            "BLOCK_SIZE": 64,
            "GRID_SIZE": 64,
            "OPTIMIZATION_LEVEL_HOST": 1,
            "MAX_REGISTERS": 60,
            "PRECISION": 64,
            "UNROLL_LOOP_1": 1,
            "UNROLL_LOOP_2": 1,
            "GPUS": 1
        },
        "time": 0.7183339595794678
    },
    {
        "parameters": {
            "OPTIMIZATION_LEVEL_DEVICE": 3,
            "USE_FAST_MATH": 0,
            "BLOCK_SIZE": 256,
            "GRID_SIZE": 64,
            "OPTIMIZATION_LEVEL_HOST": 1,
            "MAX_REGISTERS": 120,
            "PRECISION": 32,
            "UNROLL_LOOP_1": 0,
            "UNROLL_LOOP_2": 0,
            "GPUS": 1
        },
        "time": 0.7266426086425781
    },
    {
        "parameters": {
            "OPTIMIZATION_LEVEL_DEVICE": 3,
            "USE_FAST_MATH": 0,
            "BLOCK_SIZE": 128,
            "GRID_SIZE": 64,
            "OPTIMIZATION_LEVEL_HOST": 1,
            "MAX_REGISTERS": 60,
            "PRECISION": 64,
            "UNROLL_LOOP_1": 1,
            "UNROLL_LOOP_2": 1,
            "GPUS": 1
        },
        "time": 0.7045028209686279
    },
    {
        "parameters": {
            "USE_FAST_MATH": 1,
            "GRID_SIZE": 1,
            "BLOCK_SIZE": 128,
            "MAX_REGISTERS": 120,
            "UNROLL_LOOP_2": 1,
            "UNROLL_LOOP_1": 0,
            "PRECISION": 64,
            "OPTIMIZATION_LEVEL_DEVICE": 0,
            "OPTIMIZATION_LEVEL_HOST": 1,
            "GPUS": 1
        },
        "time": 3.4551613330841064
    },
    {
        "parameters": {
            "USE_FAST_MATH": 1,
            "GRID_SIZE": 16,
            "BLOCK_SIZE": 256,
            "MAX_REGISTERS": 120,
            "UNROLL_LOOP_2": 1,
            "UNROLL_LOOP_1": 0,
            "PRECISION": 64,
            "OPTIMIZATION_LEVEL_DEVICE": 3,
            "OPTIMIZATION_LEVEL_HOST": 3,
            "GPUS": 1
        },
        "time": 0.7312655448913574
    },
    {
        "parameters": {
            "USE_FAST_MATH": 0,
            "GRID_SIZE": 64,
            "BLOCK_SIZE": 128,
            "MAX_REGISTERS": 40,
            "UNROLL_LOOP_2": 0,
            "UNROLL_LOOP_1": 0,
            "PRECISION": 64,
            "OPTIMIZATION_LEVEL_DEVICE": 1,
            "OPTIMIZATION_LEVEL_HOST": 0,
            "GPUS": 1
        },
        "time": 0.739119291305542
    },
    {
        "parameters": {
            "USE_FAST_MATH": 1,
            "GRID_SIZE": 16,
            "BLOCK_SIZE": 256,
            "MAX_REGISTERS": 60,
            "UNROLL_LOOP_2": 1,
            "UNROLL_LOOP_1": 1,
            "PRECISION": 32,
            "OPTIMIZATION_LEVEL_DEVICE": 3,
            "OPTIMIZATION_LEVEL_HOST": 1,
            "GPUS": 1
        },
        "time": 0.7943894863128662
    },
    {
        "parameters": {
            "OPTIMIZATION_LEVEL_DEVICE": 3,
            "USE_FAST_MATH": 1,
            "BLOCK_SIZE": 256,
            "GRID_SIZE": 256,
            "OPTIMIZATION_LEVEL_HOST": 1,
            "MAX_REGISTERS": 60,
            "PRECISION": 64,
            "UNROLL_LOOP_1": 0,
            "UNROLL_LOOP_2": 0,
            "GPUS": 1
        },
        "time": 0.7137768268585205
    },
    {
        "parameters": {
            "OPTIMIZATION_LEVEL_DEVICE": 3,
            "USE_FAST_MATH": 0,
            "BLOCK_SIZE": 256,
            "GRID_SIZE": 256,
            "OPTIMIZATION_LEVEL_HOST": 1,
            "MAX_REGISTERS": -1,
            "PRECISION": 64,
            "UNROLL_LOOP_1": 0,
            "UNROLL_LOOP_2": 1,
            "GPUS": 1
        },
        "time": 0.7083909511566162
    },
    {
        "parameters": {
            "OPTIMIZATION_LEVEL_DEVICE": 2,
            "USE_FAST_MATH": 0,
            "BLOCK_SIZE": 128,
            "GRID_SIZE": 128,
            "OPTIMIZATION_LEVEL_HOST": 3,
            "MAX_REGISTERS": 60,
            "PRECISION": 64,
            "UNROLL_LOOP_1": 0,
            "UNROLL_LOOP_2": 0,
            "GPUS": 1
        },
        "time": 0.7309441566467285
    },
    {
        "parameters": {
            "OPTIMIZATION_LEVEL_DEVICE": 3,
            "USE_FAST_MATH": 0,
            "BLOCK_SIZE": 256,
            "GRID_SIZE": 2,
            "OPTIMIZATION_LEVEL_HOST": 1,
            "MAX_REGISTERS": 120,
            "PRECISION": 64,
            "UNROLL_LOOP_1": 1,
            "UNROLL_LOOP_2": 1,
            "GPUS": 1
        },
        "time": 0.9647128582000732
    },
    {
        "parameters": {
            "OPTIMIZATION_LEVEL_DEVICE": 3,
            "USE_FAST_MATH": 0,
            "BLOCK_SIZE": 16,
            "GRID_SIZE": 8,
            "OPTIMIZATION_LEVEL_HOST": 1,
            "MAX_REGISTERS": 60,
            "PRECISION": 32,
            "UNROLL_LOOP_1": 1,
            "UNROLL_LOOP_2": 1,
            "GPUS": 1
        },
        "time": 1.2671911716461182
    },
    {
        "parameters": {
            "OPTIMIZATION_LEVEL_DEVICE": 2,
            "USE_FAST_MATH": 0,
            "BLOCK_SIZE": 256,
            "GRID_SIZE": 2,
            "OPTIMIZATION_LEVEL_HOST": 1,
            "MAX_REGISTERS": 60,
            "PRECISION": 32,
            "UNROLL_LOOP_1": 1,
            "UNROLL_LOOP_2": 1,
            "GPUS": 1
        },
        "time": 1.0414011478424072
    },
    {
        "parameters": {
            "OPTIMIZATION_LEVEL_DEVICE": 3,
            "USE_FAST_MATH": 0,
            "BLOCK_SIZE": 128,
            "GRID_SIZE": 2,
            "OPTIMIZATION_LEVEL_HOST": 1,
            "MAX_REGISTERS": 60,
            "PRECISION": 64,
            "UNROLL_LOOP_1": 1,
            "UNROLL_LOOP_2": 1,
            "GPUS": 1
        },
        "time": 1.0418946743011475
    },
    {
        "parameters": {
            "OPTIMIZATION_LEVEL_DEVICE": 3,
            "USE_FAST_MATH": 0,
            "BLOCK_SIZE": 512,
            "GRID_SIZE": 256,
            "OPTIMIZATION_LEVEL_HOST": 1,
            "MAX_REGISTERS": 100,
            "PRECISION": 64,
            "UNROLL_LOOP_1": 1,
            "UNROLL_LOOP_2": 1,
            "GPUS": 1
        },
        "time": 0.7114441394805908
    },
    {
        "parameters": {
            "OPTIMIZATION_LEVEL_DEVICE": 3,
            "USE_FAST_MATH": 0,
            "BLOCK_SIZE": 256,
            "GRID_SIZE": 8,
            "OPTIMIZATION_LEVEL_HOST": 1,
            "MAX_REGISTERS": 60,
            "PRECISION": 32,
            "UNROLL_LOOP_1": 1,
            "UNROLL_LOOP_2": 1,
            "GPUS": 1
        },
        "time": 0.8128764629364014
    },
    {
        "parameters": {
            "OPTIMIZATION_LEVEL_DEVICE": 3,
            "USE_FAST_MATH": 0,
            "BLOCK_SIZE": 256,
            "GRID_SIZE": 256,
            "OPTIMIZATION_LEVEL_HOST": 1,
            "MAX_REGISTERS": -1,
            "PRECISION": 32,
            "UNROLL_LOOP_1": 1,
            "UNROLL_LOOP_2": 1,
            "GPUS": 1
        },
        "time": 0.7095072269439697
    },
    {
        "parameters": {
            "OPTIMIZATION_LEVEL_DEVICE": 3,
            "USE_FAST_MATH": 0,
            "BLOCK_SIZE": 256,
            "GRID_SIZE": 1,
            "OPTIMIZATION_LEVEL_HOST": 1,
            "MAX_REGISTERS": 80,
            "PRECISION": 64,
            "UNROLL_LOOP_1": 1,
            "UNROLL_LOOP_2": 0,
            "GPUS": 1
        },
        "time": 1.3236806392669678
    },
    {
        "parameters": {
            "OPTIMIZATION_LEVEL_DEVICE": 3,
            "USE_FAST_MATH": 0,
            "BLOCK_SIZE": 512,
            "GRID_SIZE": 16,
            "OPTIMIZATION_LEVEL_HOST": 1,
            "MAX_REGISTERS": 60,
            "PRECISION": 32,
            "UNROLL_LOOP_1": 1,
            "UNROLL_LOOP_2": 1,
            "GPUS": 1
        },
        "time": 0.7359936237335205
    },
    {
        "parameters": {
            "OPTIMIZATION_LEVEL_DEVICE": 3,
            "USE_FAST_MATH": 0,
            "BLOCK_SIZE": 256,
            "GRID_SIZE": 8,
            "OPTIMIZATION_LEVEL_HOST": 1,
            "MAX_REGISTERS": 40,
            "PRECISION": 64,
            "UNROLL_LOOP_1": 1,
            "UNROLL_LOOP_2": 1,
            "GPUS": 1
        },
        "time": 0.7498416900634766
    },
    {
        "parameters": {
            "OPTIMIZATION_LEVEL_DEVICE": 3,
            "USE_FAST_MATH": 0,
            "BLOCK_SIZE": 64,
            "GRID_SIZE": 2,
            "OPTIMIZATION_LEVEL_HOST": 1,
            "MAX_REGISTERS": 60,
            "PRECISION": 64,
            "UNROLL_LOOP_1": 1,
            "UNROLL_LOOP_2": 1,
            "GPUS": 1
        },
        "time": 1.2407176494598389
    },
    {
        "parameters": {
            "OPTIMIZATION_LEVEL_DEVICE": 3,
            "USE_FAST_MATH": 0,
            "BLOCK_SIZE": 256,
            "GRID_SIZE": 256,
            "OPTIMIZATION_LEVEL_HOST": 2,
            "MAX_REGISTERS": 20,
            "PRECISION": 64,
            "UNROLL_LOOP_1": 1,
            "UNROLL_LOOP_2": 1,
            "GPUS": 1
        },
        "time": 0.7328929901123047
    },
    {
        "parameters": {
            "OPTIMIZATION_LEVEL_DEVICE": 2,
            "USE_FAST_MATH": 0,
            "BLOCK_SIZE": 512,
            "GRID_SIZE": 8,
            "OPTIMIZATION_LEVEL_HOST": 2,
            "MAX_REGISTERS": 120,
            "PRECISION": 64,
            "UNROLL_LOOP_1": 0,
            "UNROLL_LOOP_2": 0,
            "GPUS": 1
        },
        "time": 0.7858915328979492
    },
    {
        "parameters": {
            "OPTIMIZATION_LEVEL_DEVICE": 3,
            "USE_FAST_MATH": 0,
            "BLOCK_SIZE": 256,
            "GRID_SIZE": 32,
            "OPTIMIZATION_LEVEL_HOST": 1,
            "MAX_REGISTERS": 40,
            "PRECISION": 64,
            "UNROLL_LOOP_1": 1,
            "UNROLL_LOOP_2": 1,
            "GPUS": 1
        },
        "time": 0.7126452922821045
    },
    {
        "parameters": {
            "OPTIMIZATION_LEVEL_DEVICE": 2,
            "USE_FAST_MATH": 0,
            "BLOCK_SIZE": 128,
            "GRID_SIZE": 16,
            "OPTIMIZATION_LEVEL_HOST": 0,
            "MAX_REGISTERS": 60,
            "PRECISION": 64,
            "UNROLL_LOOP_1": 0,
            "UNROLL_LOOP_2": 0,
            "GPUS": 1
        },
        "time": 0.777958869934082
    },
    {
        "parameters": {
            "OPTIMIZATION_LEVEL_DEVICE": 3,
            "USE_FAST_MATH": 0,
            "BLOCK_SIZE": 64,
            "GRID_SIZE": 64,
            "OPTIMIZATION_LEVEL_HOST": 1,
            "MAX_REGISTERS": 60,
            "PRECISION": 32,
            "UNROLL_LOOP_1": 0,
            "UNROLL_LOOP_2": 0,
            "GPUS": 1
        },
        "time": 0.7804934978485107
    },
    {
        "parameters": {
            "OPTIMIZATION_LEVEL_DEVICE": 3,
            "USE_FAST_MATH": 0,
            "BLOCK_SIZE": 64,
            "GRID_SIZE": 1,
            "OPTIMIZATION_LEVEL_HOST": 0,
            "MAX_REGISTERS": 80,
            "PRECISION": 64,
            "UNROLL_LOOP_1": 0,
            "UNROLL_LOOP_2": 0,
            "GPUS": 1
        },
        "time": 2.094580888748169
    },
    {
        "parameters": {
            "OPTIMIZATION_LEVEL_DEVICE": 2,
            "USE_FAST_MATH": 0,
            "BLOCK_SIZE": 512,
            "GRID_SIZE": 256,
            "OPTIMIZATION_LEVEL_HOST": 2,
            "MAX_REGISTERS": 20,
            "PRECISION": 32,
            "UNROLL_LOOP_1": 0,
            "UNROLL_LOOP_2": 0,
            "GPUS": 1
        },
        "time": 0.7023224830627441
    },
    {
        "parameters": {
            "USE_FAST_MATH": 0,
            "GRID_SIZE": 1,
            "BLOCK_SIZE": 64,
            "MAX_REGISTERS": 60,
            "UNROLL_LOOP_2": 0,
            "UNROLL_LOOP_1": 0,
            "PRECISION": 64,
            "OPTIMIZATION_LEVEL_DEVICE": 3,
            "OPTIMIZATION_LEVEL_HOST": 2,
            "GPUS": 1
        },
        "time": 2.101330518722534
    },
    {
        "parameters": {
            "USE_FAST_MATH": 1,
            "GRID_SIZE": 64,
            "BLOCK_SIZE": 64,
            "MAX_REGISTERS": 100,
            "UNROLL_LOOP_2": 1,
            "UNROLL_LOOP_1": 1,
            "PRECISION": 32,
            "OPTIMIZATION_LEVEL_DEVICE": 3,
            "OPTIMIZATION_LEVEL_HOST": 3,
            "GPUS": 1
        },
        "time": 0.7594914436340332
    },
    {
        "parameters": {
            "USE_FAST_MATH": 0,
            "GRID_SIZE": 256,
            "BLOCK_SIZE": 256,
            "MAX_REGISTERS": -1,
            "UNROLL_LOOP_2": 1,
            "UNROLL_LOOP_1": 1,
            "PRECISION": 64,
            "OPTIMIZATION_LEVEL_DEVICE": 3,
            "OPTIMIZATION_LEVEL_HOST": 0,
            "GPUS": 1
        },
        "time": 0.7252476215362549
    },
    {
        "parameters": {
            "OPTIMIZATION_LEVEL_DEVICE": 2,
            "USE_FAST_MATH": 0,
            "BLOCK_SIZE": 256,
            "GRID_SIZE": 64,
            "OPTIMIZATION_LEVEL_HOST": 1,
            "MAX_REGISTERS": 80,
            "PRECISION": 32,
            "UNROLL_LOOP_1": 1,
            "UNROLL_LOOP_2": 1,
            "GPUS": 1
        },
        "time": 0.707604169845581
    },
    {
        "parameters": {
            "OPTIMIZATION_LEVEL_DEVICE": 3,
            "USE_FAST_MATH": 0,
            "BLOCK_SIZE": 256,
            "GRID_SIZE": 1,
            "OPTIMIZATION_LEVEL_HOST": 1,
            "MAX_REGISTERS": 120,
            "PRECISION": 64,
            "UNROLL_LOOP_1": 1,
            "UNROLL_LOOP_2": 1,
            "GPUS": 1
        },
        "time": 1.220496416091919
    },
    {
        "parameters": {
            "OPTIMIZATION_LEVEL_DEVICE": 3,
            "USE_FAST_MATH": 0,
            "BLOCK_SIZE": 512,
            "GRID_SIZE": 64,
            "OPTIMIZATION_LEVEL_HOST": 1,
            "MAX_REGISTERS": 100,
            "PRECISION": 64,
            "UNROLL_LOOP_1": 1,
            "UNROLL_LOOP_2": 1,
            "GPUS": 1
        },
        "time": 0.6975958347320557
    },
    {
        "parameters": {
            "OPTIMIZATION_LEVEL_DEVICE": 3,
            "USE_FAST_MATH": 0,
            "BLOCK_SIZE": 256,
            "GRID_SIZE": 256,
            "OPTIMIZATION_LEVEL_HOST": 2,
            "MAX_REGISTERS": 120,
            "PRECISION": 64,
            "UNROLL_LOOP_1": 1,
            "UNROLL_LOOP_2": 1,
            "GPUS": 1
        },
        "time": 0.7229375839233398
    },
    {
        "parameters": {
            "OPTIMIZATION_LEVEL_DEVICE": 3,
            "USE_FAST_MATH": 0,
            "BLOCK_SIZE": 256,
            "GRID_SIZE": 1,
            "OPTIMIZATION_LEVEL_HOST": 1,
            "MAX_REGISTERS": -1,
            "PRECISION": 64,
            "UNROLL_LOOP_1": 1,
            "UNROLL_LOOP_2": 1,
            "GPUS": 1
        },
        "time": 1.2377848625183105
    },
    {
        "parameters": {
            "OPTIMIZATION_LEVEL_DEVICE": 3,
            "USE_FAST_MATH": 0,
            "BLOCK_SIZE": 256,
            "GRID_SIZE": 64,
            "OPTIMIZATION_LEVEL_HOST": 1,
            "MAX_REGISTERS": 100,
            "PRECISION": 32,
            "UNROLL_LOOP_1": 1,
            "UNROLL_LOOP_2": 1,
            "GPUS": 1
        },
        "time": 0.7153429985046387
    },
    {
        "parameters": {
            "OPTIMIZATION_LEVEL_DEVICE": 3,
            "USE_FAST_MATH": 0,
            "BLOCK_SIZE": 256,
            "GRID_SIZE": 128,
            "OPTIMIZATION_LEVEL_HOST": 1,
            "MAX_REGISTERS": 80,
            "PRECISION": 32,
            "UNROLL_LOOP_1": 1,
            "UNROLL_LOOP_2": 1,
            "GPUS": 1
        },
        "time": 0.7168755531311035
    },
    {
        "parameters": {
            "OPTIMIZATION_LEVEL_DEVICE": 3,
            "USE_FAST_MATH": 0,
            "BLOCK_SIZE": 256,
            "GRID_SIZE": 256,
            "OPTIMIZATION_LEVEL_HOST": 2,
            "MAX_REGISTERS": 100,
            "PRECISION": 64,
            "UNROLL_LOOP_1": 1,
            "UNROLL_LOOP_2": 1,
            "GPUS": 1
        },
        "time": 0.712028980255127
    },
    {
        "parameters": {
            "OPTIMIZATION_LEVEL_DEVICE": 3,
            "USE_FAST_MATH": 0,
            "BLOCK_SIZE": 64,
            "GRID_SIZE": 4,
            "OPTIMIZATION_LEVEL_HOST": 1,
            "MAX_REGISTERS": 60,
            "PRECISION": 32,
            "UNROLL_LOOP_1": 1,
            "UNROLL_LOOP_2": 1,
            "GPUS": 1
        },
        "time": 1.1630699634552002
    },
    {
        "parameters": {
            "OPTIMIZATION_LEVEL_DEVICE": 3,
            "USE_FAST_MATH": 0,
            "BLOCK_SIZE": 256,
            "GRID_SIZE": 256,
            "OPTIMIZATION_LEVEL_HOST": 2,
            "MAX_REGISTERS": 80,
            "PRECISION": 32,
            "UNROLL_LOOP_1": 1,
            "UNROLL_LOOP_2": 1,
            "GPUS": 1
        },
        "time": 0.6919548511505127
    },
    {
        "parameters": {
            "OPTIMIZATION_LEVEL_DEVICE": 3,
            "USE_FAST_MATH": 0,
            "BLOCK_SIZE": 128,
            "GRID_SIZE": 32,
            "OPTIMIZATION_LEVEL_HOST": 1,
            "MAX_REGISTERS": 80,
            "PRECISION": 64,
            "UNROLL_LOOP_1": 1,
            "UNROLL_LOOP_2": 1,
            "GPUS": 1
        },
        "time": 0.7283587455749512
    },
    {
        "parameters": {
            "OPTIMIZATION_LEVEL_DEVICE": 3,
            "USE_FAST_MATH": 0,
            "BLOCK_SIZE": 256,
            "GRID_SIZE": 16,
            "OPTIMIZATION_LEVEL_HOST": 1,
            "MAX_REGISTERS": 20,
            "PRECISION": 32,
            "UNROLL_LOOP_1": 1,
            "UNROLL_LOOP_2": 1,
            "GPUS": 1
        },
        "time": 0.7957539558410645
    },
    {
        "parameters": {
            "OPTIMIZATION_LEVEL_DEVICE": 3,
            "USE_FAST_MATH": 0,
            "BLOCK_SIZE": 128,
            "GRID_SIZE": 1,
            "OPTIMIZATION_LEVEL_HOST": 1,
            "MAX_REGISTERS": 60,
            "PRECISION": 64,
            "UNROLL_LOOP_1": 1,
            "UNROLL_LOOP_2": 1,
            "GPUS": 1
        },
        "time": 1.3908562660217285
    },
    {
        "parameters": {
            "OPTIMIZATION_LEVEL_DEVICE": 3,
            "USE_FAST_MATH": 0,
            "BLOCK_SIZE": 256,
            "GRID_SIZE": 4,
            "OPTIMIZATION_LEVEL_HOST": 0,
            "MAX_REGISTERS": 60,
            "PRECISION": 64,
            "UNROLL_LOOP_1": 1,
            "UNROLL_LOOP_2": 1,
            "GPUS": 1
        },
        "time": 0.8790433406829834
    },
    {
        "parameters": {
            "OPTIMIZATION_LEVEL_DEVICE": 3,
            "USE_FAST_MATH": 0,
            "BLOCK_SIZE": 256,
            "GRID_SIZE": 8,
            "OPTIMIZATION_LEVEL_HOST": 1,
            "MAX_REGISTERS": 80,
            "PRECISION": 64,
            "UNROLL_LOOP_1": 1,
            "UNROLL_LOOP_2": 1,
            "GPUS": 1
        },
        "time": 0.7753152847290039
    },
    {
        "parameters": {
            "OPTIMIZATION_LEVEL_DEVICE": 3,
            "USE_FAST_MATH": 0,
            "BLOCK_SIZE": 128,
            "GRID_SIZE": 8,
            "OPTIMIZATION_LEVEL_HOST": 1,
            "MAX_REGISTERS": 80,
            "PRECISION": 64,
            "UNROLL_LOOP_1": 1,
            "UNROLL_LOOP_2": 1,
            "GPUS": 1
        },
        "time": 0.7973129749298096
    },
    {
        "parameters": {
            "OPTIMIZATION_LEVEL_DEVICE": 3,
            "USE_FAST_MATH": 0,
            "BLOCK_SIZE": 128,
            "GRID_SIZE": 8,
            "OPTIMIZATION_LEVEL_HOST": 1,
            "MAX_REGISTERS": 60,
            "PRECISION": 64,
            "UNROLL_LOOP_1": 1,
            "UNROLL_LOOP_2": 1,
            "GPUS": 1
        },
        "time": 0.8032131195068359
    },
    {
        "parameters": {
            "OPTIMIZATION_LEVEL_DEVICE": 3,
            "USE_FAST_MATH": 0,
            "BLOCK_SIZE": 256,
            "GRID_SIZE": 32,
            "OPTIMIZATION_LEVEL_HOST": 1,
            "MAX_REGISTERS": 60,
            "PRECISION": 32,
            "UNROLL_LOOP_1": 1,
            "UNROLL_LOOP_2": 1,
            "GPUS": 1
        },
        "time": 0.7146968841552734
    },
    {
        "parameters": {
            "OPTIMIZATION_LEVEL_DEVICE": 3,
            "USE_FAST_MATH": 0,
            "BLOCK_SIZE": 512,
            "GRID_SIZE": 4,
            "OPTIMIZATION_LEVEL_HOST": 1,
            "MAX_REGISTERS": 20,
            "PRECISION": 64,
            "UNROLL_LOOP_1": 1,
            "UNROLL_LOOP_2": 1,
            "GPUS": 1
        },
        "time": 0.8161320686340332
    },
    {
        "parameters": {
            "OPTIMIZATION_LEVEL_DEVICE": 3,
            "USE_FAST_MATH": 0,
            "BLOCK_SIZE": 16,
            "GRID_SIZE": 4,
            "OPTIMIZATION_LEVEL_HOST": 0,
            "MAX_REGISTERS": 100,
            "PRECISION": 32,
            "UNROLL_LOOP_1": 0,
            "UNROLL_LOOP_2": 0,
            "GPUS": 1
        },
        "time": 2.1830227375030518
    },
    {
        "parameters": {
            "OPTIMIZATION_LEVEL_DEVICE": 2,
            "USE_FAST_MATH": 0,
            "BLOCK_SIZE": 256,
            "GRID_SIZE": 256,
            "OPTIMIZATION_LEVEL_HOST": 0,
            "MAX_REGISTERS": 60,
            "PRECISION": 32,
            "UNROLL_LOOP_1": 0,
            "UNROLL_LOOP_2": 0,
            "GPUS": 1
        },
        "time": 0.7510993480682373
    },
    {
        "parameters": {
            "OPTIMIZATION_LEVEL_DEVICE": 3,
            "USE_FAST_MATH": 0,
            "BLOCK_SIZE": 256,
            "GRID_SIZE": 8,
            "OPTIMIZATION_LEVEL_HOST": 1,
            "MAX_REGISTERS": 100,
            "PRECISION": 64,
            "UNROLL_LOOP_1": 1,
            "UNROLL_LOOP_2": 1,
            "GPUS": 1
        },
        "time": 0.7590451240539551
    },
    {
        "parameters": {
            "USE_FAST_MATH": 1,
            "GRID_SIZE": 4,
            "BLOCK_SIZE": 64,
            "MAX_REGISTERS": 100,
            "UNROLL_LOOP_2": 0,
            "UNROLL_LOOP_1": 0,
            "PRECISION": 64,
            "OPTIMIZATION_LEVEL_DEVICE": 3,
            "OPTIMIZATION_LEVEL_HOST": 0,
            "GPUS": 1
        },
        "time": 1.0540168285369873
    },
    {
        "parameters": {
            "USE_FAST_MATH": 1,
            "GRID_SIZE": 64,
            "BLOCK_SIZE": 128,
            "MAX_REGISTERS": 120,
            "UNROLL_LOOP_2": 0,
            "UNROLL_LOOP_1": 1,
            "PRECISION": 64,
            "OPTIMIZATION_LEVEL_DEVICE": 3,
            "OPTIMIZATION_LEVEL_HOST": 0,
            "GPUS": 1
        },
        "time": 0.7321064472198486
    },
    {
        "parameters": {
            "USE_FAST_MATH": 0,
            "GRID_SIZE": 128,
            "BLOCK_SIZE": 512,
            "MAX_REGISTERS": 120,
            "UNROLL_LOOP_2": 0,
            "UNROLL_LOOP_1": 1,
            "PRECISION": 64,
            "OPTIMIZATION_LEVEL_DEVICE": 2,
            "OPTIMIZATION_LEVEL_HOST": 0,
            "GPUS": 1
        },
        "time": 0.7315607070922852
    },
    {
        "parameters": {
            "OPTIMIZATION_LEVEL_DEVICE": 1,
            "USE_FAST_MATH": 0,
            "BLOCK_SIZE": 256,
            "GRID_SIZE": 256,
            "OPTIMIZATION_LEVEL_HOST": 1,
            "MAX_REGISTERS": 60,
            "PRECISION": 64,
            "UNROLL_LOOP_1": 1,
            "UNROLL_LOOP_2": 1,
            "GPUS": 1
        },
        "time": 0.72310471534729
    },
    {
        "parameters": {
            "OPTIMIZATION_LEVEL_DEVICE": 3,
            "USE_FAST_MATH": 0,
            "BLOCK_SIZE": 256,
            "GRID_SIZE": 1,
            "OPTIMIZATION_LEVEL_HOST": 1,
            "MAX_REGISTERS": 60,
            "PRECISION": 32,
            "UNROLL_LOOP_1": 1,
            "UNROLL_LOOP_2": 1,
            "GPUS": 1
        },
        "time": 1.3859138488769531
    },
    {
        "parameters": {
            "OPTIMIZATION_LEVEL_DEVICE": 3,
            "USE_FAST_MATH": 0,
            "BLOCK_SIZE": 512,
            "GRID_SIZE": 256,
            "OPTIMIZATION_LEVEL_HOST": 1,
            "MAX_REGISTERS": -1,
            "PRECISION": 64,
            "UNROLL_LOOP_1": 1,
            "UNROLL_LOOP_2": 1,
            "GPUS": 1
        },
        "time": 0.7274131774902344
    },
    {
        "parameters": {
            "OPTIMIZATION_LEVEL_DEVICE": 3,
            "USE_FAST_MATH": 0,
            "BLOCK_SIZE": 64,
            "GRID_SIZE": 16,
            "OPTIMIZATION_LEVEL_HOST": 1,
            "MAX_REGISTERS": 80,
            "PRECISION": 64,
            "UNROLL_LOOP_1": 1,
            "UNROLL_LOOP_2": 1,
            "GPUS": 1
        },
        "time": 0.7782964706420898
    },
    {
        "parameters": {
            "OPTIMIZATION_LEVEL_DEVICE": 3,
            "USE_FAST_MATH": 0,
            "BLOCK_SIZE": 512,
            "GRID_SIZE": 1,
            "OPTIMIZATION_LEVEL_HOST": 1,
            "MAX_REGISTERS": 60,
            "PRECISION": 32,
            "UNROLL_LOOP_1": 1,
            "UNROLL_LOOP_2": 1,
            "GPUS": 1
        },
        "time": 1.2346465587615967
    }
]